Workbook

Sheet ACCUEIL
B2: IGE — GESTION DES FRAIS DE FONCTIONNEMENT | E2: Commandes
B3: Classeur central — réservé à Administration et Finance | E3: (boutons créés par la macro d'installation)
B4: Fichier / service | C4: ="ADMINISTRATION ET FINANCE — Exercice "&C_EXERCICE
B5: Utilisateur connecté
B6: Profil
B7: Connecté depuis
B9: Mode d'emploi
B10: 1. SE CONNECTER (profil ADMIN uniquement).
B11: 2. IMPORTER LES TRANSMISSIONS : lit les fichiers TRANS_*.xlsx du dossier de transmission.
B12: Chaque ID_ECRITURE déjà présent est ignoré (doublon) sauf s'il s'agit d'une mise à jour.
B13: 3. CONTRÔLER LES ÉCRITURES : détecte les anomalies et les liste dans VERIFICATION.
B14: 4. VALIDER SANS ANOMALIE, ou VALIDER / REJETER LA SÉLECTION sur la feuille RECEPTION.
B15: 5. CONSOLIDATION et TABLEAU_DE_BORD ne comptent que les écritures VALIDEE.
B16: 6. Comptes : saisir le mot de passe initial (col. H de UTILISATEURS) puis CHIFFRER LES MOTS DE PASSE.
B17: 7. GÉNÉRER LES FICHIERS SERVICES : crée/actualise un fichier par service à partir du modèle.

Sheet RECEPTION
A1: RÉCEPTION DES ÉCRITURES TRANSMISES PAR LES SERVICES
A2: Alimentée par IMPORTER LES TRANSMISSIONS. Sélectionnez des lignes puis VALIDER / REJETER LA SÉLECTION.
A3: ID_ECRITURE | B3: N° | C3: Date | D3: Exercice | E3: Mois | F3: Service | G3: Code rubrique | H3: Catégorie | I3: Description | J3: Fournisseur / bénéficiaire | K3: N° pièce | L3: Mode de paiement | M3: Statut | N3: Entrée | O3: Sortie | P3: Utilisateur | Q3: Date de saisie | R3: Observations | S3: ID_TRANSMISSION | T3: FICHIER_SOURCE | U3: DATE_IMPORT | V3: IMPORTE_PAR | W3: ETAT_VERIFICATION | X3: ANOMALIES / MOTIF
A4: 9990TEST-2026-000001 | W4: VALIDEE
A5: 9990TEST-2026-000002 | W5: VALIDEE
A6: 9990TEST-2026-000003 | W6: REJETEE | X6: Pièce manquante

Sheet VERIFICATION
A1: VÉRIFICATION DES ÉCRITURES REÇUES
A2: Synthèse automatique ; la liste des anomalies est produite par CONTRÔLER LES ÉCRITURES.
A3: État | B3: Nombre d'écritures | C3: Montant des sorties
A4: A VERIFIER | B4: =COUNTIF(RECEPTION!$W$4:$W$50000,A4) | C4: =SUMIFS(RECEPTION!$O$4:$O$50000,RECEPTION!$W$4:$W$50000,A4)
A5: VALIDEE | B5: =COUNTIF(RECEPTION!$W$4:$W$50000,A5) | C5: =SUMIFS(RECEPTION!$O$4:$O$50000,RECEPTION!$W$4:$W$50000,A5)
A6: REJETEE | B6: =COUNTIF(RECEPTION!$W$4:$W$50000,A6) | C6: =SUMIFS(RECEPTION!$O$4:$O$50000,RECEPTION!$W$4:$W$50000,A6)
A7: Écritures avec anomalie | B7: =COUNTIFS(RECEPTION!$W$4:$W$50000,"A VERIFIER",RECEPTION!$X$4:$X$50000,"<>",RECEPTION!$X$4:$X$50000,"<>Aucune anomalie")
A9: ID_ECRITURE | B9: Service | C9: N° | D9: Date | E9: Entrée | F9: Sortie | G9: Anomalie(s) | H9: Ligne RECEPTION

Sheet CONSOLIDATION
A1: CONSOLIDATION PAR SERVICE (écritures VALIDEE uniquement, CDF)
A3: Service | B3: Budget annuel | C3: Entrées | D3: Sorties payées | E3: Engagements | F3: Total consommé | G3: Disponible | H3: Taux d'exécution | I3: Solde de caisse | J3: À vérifier | K3: Rejetées | L3: Dernier import reçu | N3: Catégorie | O3: Sorties payées | P3: Engagements | Q3: Total
A4: TOTAL | B4: =SUM(B5:B44) | C4: =SUM(C5:C44) | D4: =SUM(D5:D44) | E4: =SUM(E5:E44) | F4: =SUM(F5:F44) | G4: =SUM(G5:G44) | H4: =IF(B4=0,"",F4/B4) | I4: =SUM(I5:I44) | J4: =SUM(J5:J44) | K4: =SUM(K5:K44) | N4: TOTAL | O4: =SUM(O5:O24) | P4: =SUM(P5:P24) | Q4: =SUM(Q5:Q24)
A5: =IF(PARAMETRES!E4="","",PARAMETRES!E4) | B5: =IF(A5="","",SUMIFS(BUDGETS_SERVICES!$E$4:$E$20000,BUDGETS_SERVICES!$A$4:$A$20000,A5)) | C5: =IF(A5="","",SUMIFS(RECEPTION!$N$4:$N$50000,RECEPTION!$F$4:$F$50000,A5,RECEPTION!$W$4:$W$50000,"VALIDEE")) | D5: =IF(A5="","",SUMIFS(RECEPTION!$O$4:$O$50000,RECEPTION!$F$4:$F$50000,A5,RECEPTION!$M$4:$M$50000,"Payée",RECEPTION!$W$4:$W$50000,"VALIDEE")) | E5: =IF(A5="","",SUMIFS(RECEPTION!$O$4:$O$50000,RECEPTION!$F$4:$F$50000,A5,RECEPTION!$M$4:$M$50000,"Engagée",RECEPTION!$W$4:$W$50000,"VALIDEE")) | F5: =IF(A5="","",D5+E5) | G5: =IF(A5="","",B5-F5) | H5: =IF(OR(A5="",N(B5)=0),"",F5/B5) | I5: =IF(A5="","",C5-D5) | J5: =IF(A5="","",COUNTIFS(RECEPTION!$F$4:$F$50000,A5,RECEPTION!$W$4:$W$50000,"A VERIFIER")) | K5: =IF(A5="","",COUNTIFS(RECEPTION!$F$4:$F$50000,A5,RECEPTION!$W$4:$W$50000,"REJETEE")) | L5: =IF(A5="","",IF(_xlfn.MAXIFS(JOURNAL_IMPORTS!$A$4:$A$5000,JOURNAL_IMPORTS!$C$4:$C$5000,A5)=0,"Aucune",_xlfn.MAXIFS(JOURNAL_IMPORTS!$A$4:$A$5000,JOURNAL_IMPORTS!$C$4:$C$5000,A5))) | N5: =IF(PARAMETRES!L4="","",PARAMETRES!L4) | O5: =IF(N5="","",SUMIFS(RECEPTION!$O$4:$O$50000,RECEPTION!$H$4:$H$50000,N5,RECEPTION!$M$4:$M$50000,"Payée",RECEPTION!$W$4:$W$50000,"VALIDEE")) | P5: =IF(N5="","",SUMIFS(RECEPTION!$O$4:$O$50000,RECEPTION!$H$4:$H$50000,N5,RECEPTION!$M$4:$M$50000,"Engagée",RECEPTION!$W$4:$W$50000,"VALIDEE")) | Q5: =IF(N5="","",O5+P5)
A6: =IF(PARAMETRES!E5="","",PARAMETRES!E5) | B6: =IF(A6="","",SUMIFS(BUDGETS_SERVICES!$E$4:$E$20000,BUDGETS_SERVICES!$A$4:$A$20000,A6)) | C6: =IF(A6="","",SUMIFS(RECEPTION!$N$4:$N$50000,RECEPTION!$F$4:$F$50000,A6,RECEPTION!$W$4:$W$50000,"VALIDEE")) | D6: =IF(A6="","",SUMIFS(RECEPTION!$O$4:$O$50000,RECEPTION!$F$4:$F$50000,A6,RECEPTION!$M$4:$M$50000,"Payée",RECEPTION!$W$4:$W$50000,"VALIDEE")) | E6: =IF(A6="","",SUMIFS(RECEPTION!$O$4:$O$50000,RECEPTION!$F$4:$F$50000,A6,RECEPTION!$M$4:$M$50000,"Engagée",RECEPTION!$W$4:$W$50000,"VALIDEE")) | F6: =IF(A6="","",D6+E6) | G6: =IF(A6="","",B6-F6) | H6: =IF(OR(A6="",N(B6)=0),"",F6/B6) | I6: =IF(A6="","",C6-D6) | J6: =IF(A6="","",COUNTIFS(RECEPTION!$F$4:$F$50000,A6,RECEPTION!$W$4:$W$50000,"A VERIFIER")) | K6: =IF(A6="","",COUNTIFS(RECEPTION!$F$4:$F$50000,A6,RECEPTION!$W$4:$W$50000,"REJETEE")) | L6: =IF(A6="","",IF(_xlfn.MAXIFS(JOURNAL_IMPORTS!$A$4:$A$5000,JOURNAL_IMPORTS!$C$4:$C$5000,A6)=0,"Aucune",_xlfn.MAXIFS(JOURNAL_IMPORTS!$A$4:$A$5000,JOURNAL_IMPORTS!$C$4:$C$5000,A6))) | N6: =IF(PARAMETRES!L5="","",PARAMETRES!L5) | O6: =IF(N6="","",SUMIFS(RECEPTION!$O$4:$O$50000,RECEPTION!$H$4:$H$50000,N6,RECEPTION!$M$4:$M$50000,"Payée",RECEPTION!$W$4:$W$50000,"VALIDEE")) | P6: =IF(N6="","",SUMIFS(RECEPTION!$O$4:$O$50000,RECEPTION!$H$4:$H$50000,N6,RECEPTION!$M$4:$M$50000,"Engagée",RECEPTION!$W$4:$W$50000,"VALIDEE")) | Q6: =IF(N6="","",O6+P6)
A7: =IF(PARAMETRES!E6="","",PARAMETRES!E6) | B7: =IF(A7="","",SUMIFS(BUDGETS_SERVICES!$E$4:$E$20000,BUDGETS_SERVICES!$A$4:$A$20000,A7)) | C7: =IF(A7="","",SUMIFS(RECEPTION!$N$4:$N$50000,RECEPTION!$F$4:$F$50000,A7,RECEPTION!$W$4:$W$50000,"VALIDEE")) | D7: =IF(A7="","",SUMIFS(RECEPTION!$O$4:$O$50000,RECEPTION!$F$4:$F$50000,A7,RECEPTION!$M$4:$M$50000,"Payée",RECEPTION!$W$4:$W$50000,"VALIDEE")) | E7: =IF(A7="","",SUMIFS(RECEPTION!$O$4:$O$50000,RECEPTION!$F$4:$F$50000,A7,RECEPTION!$M$4:$M$50000,"Engagée",RECEPTION!$W$4:$W$50000,"VALIDEE")) | F7: =IF(A7="","",D7+E7) | G7: =IF(A7="","",B7-F7) | H7: =IF(OR(A7="",N(B7)=0),"",F7/B7) | I7: =IF(A7="","",C7-D7) | J7: =IF(A7="","",COUNTIFS(RECEPTION!$F$4:$F$50000,A7,RECEPTION!$W$4:$W$50000,"A VERIFIER")) | K7: =IF(A7="","",COUNTIFS(RECEPTION!$F$4:$F$50000,A7,RECEPTION!$W$4:$W$50000,"REJETEE")) | L7: =IF(A7="","",IF(_xlfn.MAXIFS(JOURNAL_IMPORTS!$A$4:$A$5000,JOURNAL_IMPORTS!$C$4:$C$5000,A7)=0,"Aucune",_xlfn.MAXIFS(JOURNAL_IMPORTS!$A$4:$A$5000,JOURNAL_IMPORTS!$C$4:$C$5000,A7))) | N7: =IF(PARAMETRES!L6="","",PARAMETRES!L6) | O7: =IF(N7="","",SUMIFS(RECEPTION!$O$4:$O$50000,RECEPTION!$H$4:$H$50000,N7,RECEPTION!$M$4:$M$50000,"Payée",RECEPTION!$W$4:$W$50000,"VALIDEE")) | P7: =IF(N7="","",SUMIFS(RECEPTION!$O$4:$O$50000,RECEPTION!$H$4:$H$50000,N7,RECEPTION!$M$4:$M$50000,"Engagée",RECEPTION!$W$4:$W$50000,"VALIDEE")) | Q7: =IF(N7="","",O7+P7)
A8: =IF(PARAMETRES!E7="","",PARAMETRES!E7) | B8: =IF(A8="","",SUMIFS(BUDGETS_SERVICES!$E$4:$E$20000,BUDGETS_SERVICES!$A$4:$A$20000,A8)) | C8: =IF(A8="","",SUMIFS(RECEPTION!$N$4:$N$50000,RECEPTION!$F$4:$F$50000,A8,RECEPTION!$W$4:$W$50000,"VALIDEE")) | D8: =IF(A8="","",SUMIFS(RECEPTION!$O$4:$O$50000,RECEPTION!$F$4:$F$50000,A8,RECEPTION!$M$4:$M$50000,"Payée",RECEPTION!$W$4:$W$50000,"VALIDEE")) | E8: =IF(A8="","",SUMIFS(RECEPTION!$O$4:$O$50000,RECEPTION!$F$4:$F$50000,A8,RECEPTION!$M$4:$M$50000,"Engagée",RECEPTION!$W$4:$W$50000,"VALIDEE")) | F8: =IF(A8="","",D8+E8) | G8: =IF(A8="","",B8-F8) | H8: =IF(OR(A8="",N(B8)=0),"",F8/B8) | I8: =IF(A8="","",C8-D8) | J8: =IF(A8="","",COUNTIFS(RECEPTION!$F$4:$F$50000,A8,RECEPTION!$W$4:$W$50000,"A VERIFIER")) | K8: =IF(A8="","",COUNTIFS(RECEPTION!$F$4:$F$50000,A8,RECEPTION!$W$4:$W$50000,"REJETEE")) | L8: =IF(A8="","",IF(_xlfn.MAXIFS(JOURNAL_IMPORTS!$A$4:$A$5000,JOURNAL_IMPORTS!$C$4:$C$5000,A8)=0,"Aucune",_xlfn.MAXIFS(JOURNAL_IMPORTS!$A$4:$A$5000,JOURNAL_IMPORTS!$C$4:$C$5000,A8))) | N8: =IF(PARAMETRES!L7="","",PARAMETRES!L7) | O8: =IF(N8="","",SUMIFS(RECEPTION!$O$4:$O$50000,RECEPTION!$H$4:$H$50000,N8,RECEPTION!$M$4:$M$50000,"Payée",RECEPTION!$W$4:$W$50000,"VALIDEE")) | P8: =IF(N8="","",SUMIFS(RECEPTION!$O$4:$O$50000,RECEPTION!$H$4:$H$50000,N8,RECEPTION!$M$4:$M$50000,"Engagée",RECEPTION!$W$4:$W$50000,"VALIDEE")) | Q8: =IF(N8="","",O8+P8)
A9: =IF(PARAMETRES!E8="","",PARAMETRES!E8) | B9: =IF(A9="","",SUMIFS(BUDGETS_SERVICES!$E$4:$E$20000,BUDGETS_SERVICES!$A$4:$A$20000,A9)) | C9: =IF(A9="","",SUMIFS(RECEPTION!$N$4:$N$50000,RECEPTION!$F$4:$F$50000,A9,RECEPTION!$W$4:$W$50000,"VALIDEE")) | D9: =IF(A9="","",SUMIFS(RECEPTION!$O$4:$O$50000,RECEPTION!$F$4:$F$50000,A9,RECEPTION!$M$4:$M$50000,"Payée",RECEPTION!$W$4:$W$50000,"VALIDEE")) | E9: =IF(A9="","",SUMIFS(RECEPTION!$O$4:$O$50000,RECEPTION!$F$4:$F$50000,A9,RECEPTION!$M$4:$M$50000,"Engagée",RECEPTION!$W$4:$W$50000,"VALIDEE")) | F9: =IF(A9="","",D9+E9) | G9: =IF(A9="","",B9-F9) | H9: =IF(OR(A9="",N(B9)=0),"",F9/B9) | I9: =IF(A9="","",C9-D9) | J9: =IF(A9="","",COUNTIFS(RECEPTION!$F$4:$F$50000,A9,RECEPTION!$W$4:$W$50000,"A VERIFIER")) | K9: =IF(A9="","",COUNTIFS(RECEPTION!$F$4:$F$50000,A9,RECEPTION!$W$4:$W$50000,"REJETEE")) | L9: =IF(A9="","",IF(_xlfn.MAXIFS(JOURNAL_IMPORTS!$A$4:$A$5000,JOURNAL_IMPORTS!$C$4:$C$5000,A9)=0,"Aucune",_xlfn.MAXIFS(JOURNAL_IMPORTS!$A$4:$A$5000,JOURNAL_IMPORTS!$C$4:$C$5000,A9))) | N9: =IF(PARAMETRES!L8="","",PARAMETRES!L8) | O9: =IF(N9="","",SUMIFS(RECEPTION!$O$4:$O$50000,RECEPTION!$H$4:$H$50000,N9,RECEPTION!$M$4:$M$50000,"Payée",RECEPTION!$W$4:$W$50000,"VALIDEE")) | P9: =IF(N9="","",SUMIFS(RECEPTION!$O$4:$O$50000,RECEPTION!$H$4:$H$50000,N9,RECEPTION!$M$4:$M$50000,"Engagée",RECEPTION!$W$4:$W$50000,"VALIDEE")) | Q9: =IF(N9="","",O9+P9)
A10: =IF(PARAMETRES!E9="","",PARAMETRES!E9) | B10: =IF(A10="","",SUMIFS(BUDGETS_SERVICES!$E$4:$E$20000,BUDGETS_SERVICES!$A$4:$A$20000,A10)) | C10: =IF(A10="","",SUMIFS(RECEPTION!$N$4:$N$50000,RECEPTION!$F$4:$F$50000,A10,RECEPTION!$W$4:$W$50000,"VALIDEE")) | D10: =IF(A10="","",SUMIFS(RECEPTION!$O$4:$O$50000,RECEPTION!$F$4:$F$50000,A10,RECEPTION!$M$4:$M$50000,"Payée",RECEPTION!$W$4:$W$50000,"VALIDEE")) | E10: =IF(A10="","",SUMIFS(RECEPTION!$O$4:$O$50000,RECEPTION!$F$4:$F$50000,A10,RECEPTION!$M$4:$M$50000,"Engagée",RECEPTION!$W$4:$W$50000,"VALIDEE")) | F10: =IF(A10="","",D10+E10) | G10: =IF(A10="","",B10-F10) | H10: =IF(OR(A10="",N(B10)=0),"",F10/B10) | I10: =IF(A10="","",C10-D10) | J10: =IF(A10="","",COUNTIFS(RECEPTION!$F$4:$F$50000,A10,RECEPTION!$W$4:$W$50000,"A VERIFIER")) | K10: =IF(A10="","",COUNTIFS(RECEPTION!$F$4:$F$50000,A10,RECEPTION!$W$4:$W$50000,"REJETEE")) | L10: =IF(A10="","",IF(_xlfn.MAXIFS(JOURNAL_IMPORTS!$A$4:$A$5000,JOURNAL_IMPORTS!$C$4:$C$5000,A10)=0,"Aucune",_xlfn.MAXIFS(JOURNAL_IMPORTS!$A$4:$A$5000,JOURNAL_IMPORTS!$C$4:$C$5000,A10))) | N10: =IF(PARAMETRES!L9="","",PARAMETRES!L9) | O10: =IF(N10="","",SUMIFS(RECEPTION!$O$4:$O$50000,RECEPTION!$H$4:$H$50000,N10,RECEPTION!$M$4:$M$50000,"Payée",RECEPTION!$W$4:$W$50000,"VALIDEE")) | P10: =IF(N10="","",SUMIFS(RECEPTION!$O$4:$O$50000,RECEPTION!$H$4:$H$50000,N10,RECEPTION!$M$4:$M$50000,"Engagée",RECEPTION!$W$4:$W$50000,"VALIDEE")) | Q10: =IF(N10="","",O10+P10)
A11: =IF(PARAMETRES!E10="","",PARAMETRES!E10) | B11: =IF(A11="","",SUMIFS(BUDGETS_SERVICES!$E$4:$E$20000,BUDGETS_SERVICES!$A$4:$A$20000,A11)) | C11: =IF(A11="","",SUMIFS(RECEPTION!$N$4:$N$50000,RECEPTION!$F$4:$F$50000,A11,RECEPTION!$W$4:$W$50000,"VALIDEE")) | D11: =IF(A11="","",SUMIFS(RECEPTION!$O$4:$O$50000,RECEPTION!$F$4:$F$50000,A11,RECEPTION!$M$4:$M$50000,"Payée",RECEPTION!$W$4:$W$50000,"VALIDEE")) | E11: =IF(A11="","",SUMIFS(RECEPTION!$O$4:$O$50000,RECEPTION!$F$4:$F$50000,A11,RECEPTION!$M$4:$M$50000,"Engagée",RECEPTION!$W$4:$W$50000,"VALIDEE")) | F11: =IF(A11="","",D11+E11) | G11: =IF(A11="","",B11-F11) | H11: =IF(OR(A11="",N(B11)=0),"",F11/B11) | I11: =IF(A11="","",C11-D11) | J11: =IF(A11="","",COUNTIFS(RECEPTION!$F$4:$F$50000,A11,RECEPTION!$W$4:$W$50000,"A VERIFIER")) | K11: =IF(A11="","",COUNTIFS(RECEPTION!$F$4:$F$50000,A11,RECEPTION!$W$4:$W$50000,"REJETEE")) | L11: =IF(A11="","",IF(_xlfn.MAXIFS(JOURNAL_IMPORTS!$A$4:$A$5000,JOURNAL_IMPORTS!$C$4:$C$5000,A11)=0,"Aucune",_xlfn.MAXIFS(JOURNAL_IMPORTS!$A$4:$A$5000,JOURNAL_IMPORTS!$C$4:$C$5000,A11))) | N11: =IF(PARAMETRES!L10="","",PARAMETRES!L10) | O11: =IF(N11="","",SUMIFS(RECEPTION!$O$4:$O$50000,RECEPTION!$H$4:$H$50000,N11,RECEPTION!$M$4:$M$50000,"Payée",RECEPTION!$W$4:$W$50000,"VALIDEE")) | P11: =IF(N11="","",SUMIFS(RECEPTION!$O$4:$O$50000,RECEPTION!$H$4:$H$50000,N11,RECEPTION!$M$4:$M$50000,"Engagée",RECEPTION!$W$4:$W$50000,"VALIDEE")) | Q11: =IF(N11="","",O11+P11)
A12: =IF(PARAMETRES!E11="","",PARAMETRES!E11) | B12: =IF(A12="","",SUMIFS(BUDGETS_SERVICES!$E$4:$E$20000,BUDGETS_SERVICES!$A$4:$A$20000,A12)) | C12: =IF(A12="","",SUMIFS(RECEPTION!$N$4:$N$50000,RECEPTION!$F$4:$F$50000,A12,RECEPTION!$W$4:$W$50000,"VALIDEE")) | D12: =IF(A12="","",SUMIFS(RECEPTION!$O$4:$O$50000,RECEPTION!$F$4:$F$50000,A12,RECEPTION!$M$4:$M$50000,"Payée",RECEPTION!$W$4:$W$50000,"VALIDEE")) | E12: =IF(A12="","",SUMIFS(RECEPTION!$O$4:$O$50000,RECEPTION!$F$4:$F$50000,A12,RECEPTION!$M$4:$M$50000,"Engagée",RECEPTION!$W$4:$W$50000,"VALIDEE")) | F12: =IF(A12="","",D12+E12) | G12: =IF(A12="","",B12-F12) | H12: =IF(OR(A12="",N(B12)=0),"",F12/B12) | I12: =IF(A12="","",C12-D12) | J12: =IF(A12="","",COUNTIFS(RECEPTION!$F$4:$F$50000,A12,RECEPTION!$W$4:$W$50000,"A VERIFIER")) | K12: =IF(A12="","",COUNTIFS(RECEPTION!$F$4:$F$50000,A12,RECEPTION!$W$4:$W$50000,"REJETEE")) | L12: =IF(A12="","",IF(_xlfn.MAXIFS(JOURNAL_IMPORTS!$A$4:$A$5000,JOURNAL_IMPORTS!$C$4:$C$5000,A12)=0,"Aucune",_xlfn.MAXIFS(JOURNAL_IMPORTS!$A$4:$A$5000,JOURNAL_IMPORTS!$C$4:$C$5000,A12))) | N12: =IF(PARAMETRES!L11="","",PARAMETRES!L11) | O12: =IF(N12="","",SUMIFS(RECEPTION!$O$4:$O$50000,RECEPTION!$H$4:$H$50000,N12,RECEPTION!$M$4:$M$50000,"Payée",RECEPTION!$W$4:$W$50000,"VALIDEE")) | P12: =IF(N12="","",SUMIFS(RECEPTION!$O$4:$O$50000,RECEPTION!$H$4:$H$50000,N12,RECEPTION!$M$4:$M$50000,"Engagée",RECEPTION!$W$4:$W$50000,"VALIDEE")) | Q12: =IF(N12="","",O12+P12)
A13: =IF(PARAMETRES!E12="","",PARAMETRES!E12) | B13: =IF(A13="","",SUMIFS(BUDGETS_SERVICES!$E$4:$E$20000,BUDGETS_SERVICES!$A$4:$A$20000,A13)) | C13: =IF(A13="","",SUMIFS(RECEPTION!$N$4:$N$50000,RECEPTION!$F$4:$F$50000,A13,RECEPTION!$W$4:$W$50000,"VALIDEE")) | D13: =IF(A13="","",SUMIFS(RECEPTION!$O$4:$O$50000,RECEPTION!$F$4:$F$50000,A13,RECEPTION!$M$4:$M$50000,"Payée",RECEPTION!$W$4:$W$50000,"VALIDEE")) | E13: =IF(A13="","",SUMIFS(RECEPTION!$O$4:$O$50000,RECEPTION!$F$4:$F$50000,A13,RECEPTION!$M$4:$M$50000,"Engagée",RECEPTION!$W$4:$W$50000,"VALIDEE")) | F13: =IF(A13="","",D13+E13) | G13: =IF(A13="","",B13-F13) | H13: =IF(OR(A13="",N(B13)=0),"",F13/B13) | I13: =IF(A13="","",C13-D13) | J13: =IF(A13="","",COUNTIFS(RECEPTION!$F$4:$F$50000,A13,RECEPTION!$W$4:$W$50000,"A VERIFIER")) | K13: =IF(A13="","",COUNTIFS(RECEPTION!$F$4:$F$50000,A13,RECEPTION!$W$4:$W$50000,"REJETEE")) | L13: =IF(A13="","",IF(_xlfn.MAXIFS(JOURNAL_IMPORTS!$A$4:$A$5000,JOURNAL_IMPORTS!$C$4:$C$5000,A13)=0,"Aucune",_xlfn.MAXIFS(JOURNAL_IMPORTS!$A$4:$A$5000,JOURNAL_IMPORTS!$C$4:$C$5000,A13))) | N13: =IF(PARAMETRES!L12="","",PARAMETRES!L12) | O13: =IF(N13="","",SUMIFS(RECEPTION!$O$4:$O$50000,RECEPTION!$H$4:$H$50000,N13,RECEPTION!$M$4:$M$50000,"Payée",RECEPTION!$W$4:$W$50000,"VALIDEE")) | P13: =IF(N13="","",SUMIFS(RECEPTION!$O$4:$O$50000,RECEPTION!$H$4:$H$50000,N13,RECEPTION!$M$4:$M$50000,"Engagée",RECEPTION!$W$4:$W$50000,"VALIDEE")) | Q13: =IF(N13="","",O13+P13)
A14: =IF(PARAMETRES!E13="","",PARAMETRES!E13) | B14: =IF(A14="","",SUMIFS(BUDGETS_SERVICES!$E$4:$E$20000,BUDGETS_SERVICES!$A$4:$A$20000,A14)) | C14: =IF(A14="","",SUMIFS(RECEPTION!$N$4:$N$50000,RECEPTION!$F$4:$F$50000,A14,RECEPTION!$W$4:$W$50000,"VALIDEE")) | D14: =IF(A14="","",SUMIFS(RECEPTION!$O$4:$O$50000,RECEPTION!$F$4:$F$50000,A14,RECEPTION!$M$4:$M$50000,"Payée",RECEPTION!$W$4:$W$50000,"VALIDEE")) | E14: =IF(A14="","",SUMIFS(RECEPTION!$O$4:$O$50000,RECEPTION!$F$4:$F$50000,A14,RECEPTION!$M$4:$M$50000,"Engagée",RECEPTION!$W$4:$W$50000,"VALIDEE")) | F14: =IF(A14="","",D14+E14) | G14: =IF(A14="","",B14-F14) | H14: =IF(OR(A14="",N(B14)=0),"",F14/B14) | I14: =IF(A14="","",C14-D14) | J14: =IF(A14="","",COUNTIFS(RECEPTION!$F$4:$F$50000,A14,RECEPTION!$W$4:$W$50000,"A VERIFIER")) | K14: =IF(A14="","",COUNTIFS(RECEPTION!$F$4:$F$50000,A14,RECEPTION!$W$4:$W$50000,"REJETEE")) | L14: =IF(A14="","",IF(_xlfn.MAXIFS(JOURNAL_IMPORTS!$A$4:$A$5000,JOURNAL_IMPORTS!$C$4:$C$5000,A14)=0,"Aucune",_xlfn.MAXIFS(JOURNAL_IMPORTS!$A$4:$A$5000,JOURNAL_IMPORTS!$C$4:$C$5000,A14))) | N14: =IF(PARAMETRES!L13="","",PARAMETRES!L13) | O14: =IF(N14="","",SUMIFS(RECEPTION!$O$4:$O$50000,RECEPTION!$H$4:$H$50000,N14,RECEPTION!$M$4:$M$50000,"Payée",RECEPTION!$W$4:$W$50000,"VALIDEE")) | P14: =IF(N14="","",SUMIFS(RECEPTION!$O$4:$O$50000,RECEPTION!$H$4:$H$50000,N14,RECEPTION!$M$4:$M$50000,"Engagée",RECEPTION!$W$4:$W$50000,"VALIDEE")) | Q14: =IF(N14="","",O14+P14)
A15: =IF(PARAMETRES!E14="","",PARAMETRES!E14) | B15: =IF(A15="","",SUMIFS(BUDGETS_SERVICES!$E$4:$E$20000,BUDGETS_SERVICES!$A$4:$A$20000,A15)) | C15: =IF(A15="","",SUMIFS(RECEPTION!$N$4:$N$50000,RECEPTION!$F$4:$F$50000,A15,RECEPTION!$W$4:$W$50000,"VALIDEE")) | D15: =IF(A15="","",SUMIFS(RECEPTION!$O$4:$O$50000,RECEPTION!$F$4:$F$50000,A15,RECEPTION!$M$4:$M$50000,"Payée",RECEPTION!$W$4:$W$50000,"VALIDEE")) | E15: =IF(A15="","",SUMIFS(RECEPTION!$O$4:$O$50000,RECEPTION!$F$4:$F$50000,A15,RECEPTION!$M$4:$M$50000,"Engagée",RECEPTION!$W$4:$W$50000,"VALIDEE")) | F15: =IF(A15="","",D15+E15) | G15: =IF(A15="","",B15-F15) | H15: =IF(OR(A15="",N(B15)=0),"",F15/B15) | I15: =IF(A15="","",C15-D15) | J15: =IF(A15="","",COUNTIFS(RECEPTION!$F$4:$F$50000,A15,RECEPTION!$W$4:$W$50000,"A VERIFIER")) | K15: =IF(A15="","",COUNTIFS(RECEPTION!$F$4:$F$50000,A15,RECEPTION!$W$4:$W$50000,"REJETEE")) | L15: =IF(A15="","",IF(_xlfn.MAXIFS(JOURNAL_IMPORTS!$A$4:$A$5000,JOURNAL_IMPORTS!$C$4:$C$5000,A15)=0,"Aucune",_xlfn.MAXIFS(JOURNAL_IMPORTS!$A$4:$A$5000,JOURNAL_IMPORTS!$C$4:$C$5000,A15))) | N15: =IF(PARAMETRES!L14="","",PARAMETRES!L14) | O15: =IF(N15="","",SUMIFS(RECEPTION!$O$4:$O$50000,RECEPTION!$H$4:$H$50000,N15,RECEPTION!$M$4:$M$50000,"Payée",RECEPTION!$W$4:$W$50000,"VALIDEE")) | P15: =IF(N15="","",SUMIFS(RECEPTION!$O$4:$O$50000,RECEPTION!$H$4:$H$50000,N15,RECEPTION!$M$4:$M$50000,"Engagée",RECEPTION!$W$4:$W$50000,"VALIDEE")) | Q15: =IF(N15="","",O15+P15)
A16: =IF(PARAMETRES!E15="","",PARAMETRES!E15) | B16: =IF(A16="","",SUMIFS(BUDGETS_SERVICES!$E$4:$E$20000,BUDGETS_SERVICES!$A$4:$A$20000,A16)) | C16: =IF(A16="","",SUMIFS(RECEPTION!$N$4:$N$50000,RECEPTION!$F$4:$F$50000,A16,RECEPTION!$W$4:$W$50000,"VALIDEE")) | D16: =IF(A16="","",SUMIFS(RECEPTION!$O$4:$O$50000,RECEPTION!$F$4:$F$50000,A16,RECEPTION!$M$4:$M$50000,"Payée",RECEPTION!$W$4:$W$50000,"VALIDEE")) | E16: =IF(A16="","",SUMIFS(RECEPTION!$O$4:$O$50000,RECEPTION!$F$4:$F$50000,A16,RECEPTION!$M$4:$M$50000,"Engagée",RECEPTION!$W$4:$W$50000,"VALIDEE")) | F16: =IF(A16="","",D16+E16) | G16: =IF(A16="","",B16-F16) | H16: =IF(OR(A16="",N(B16)=0),"",F16/B16) | I16: =IF(A16="","",C16-D16) | J16: =IF(A16="","",COUNTIFS(RECEPTION!$F$4:$F$50000,A16,RECEPTION!$W$4:$W$50000,"A VERIFIER")) | K16: =IF(A16="","",COUNTIFS(RECEPTION!$F$4:$F$50000,A16,RECEPTION!$W$4:$W$50000,"REJETEE")) | L16: =IF(A16="","",IF(_xlfn.MAXIFS(JOURNAL_IMPORTS!$A$4:$A$5000,JOURNAL_IMPORTS!$C$4:$C$5000,A16)=0,"Aucune",_xlfn.MAXIFS(JOURNAL_IMPORTS!$A$4:$A$5000,JOURNAL_IMPORTS!$C$4:$C$5000,A16))) | N16: =IF(PARAMETRES!L15="","",PARAMETRES!L15) | O16: =IF(N16="","",SUMIFS(RECEPTION!$O$4:$O$50000,RECEPTION!$H$4:$H$50000,N16,RECEPTION!$M$4:$M$50000,"Payée",RECEPTION!$W$4:$W$50000,"VALIDEE")) | P16: =IF(N16="","",SUMIFS(RECEPTION!$O$4:$O$50000,RECEPTION!$H$4:$H$50000,N16,RECEPTION!$M$4:$M$50000,"Engagée",RECEPTION!$W$4:$W$50000,"VALIDEE")) | Q16: =IF(N16="","",O16+P16)
... A24: =IF(PARAMETRES!E23="","",PARAMETRES!E23) | B24: =IF(A24="","",SUMIFS(BUDGETS_SERVICES!$E$4:$E$20000,BUDGETS_SERVICES!$A$4:$A$20000,A24)) | C24: =IF(A24="","",SUMIFS(RECEPTION!$N$4:$N$50000,RECEPTION!$F$4:$F$50000,A24,RECEPTION!$W$4:$W$50000,"VALIDEE")) | D24: =IF(A24="","",SUMIFS(RECEPTION!$O$4:$O$50000,RECEPTION!$F$4:$F$50000,A24,RECEPTION!$M$4:$M$50000,"Payée",RECEPTION!$W$4:$W$50000,"VALIDEE")) | E24: =IF(A24="","",SUMIFS(RECEPTION!$O$4:$O$50000,RECEPTION!$F$4:$F$50000,A24,RECEPTION!$M$4:$M$50000,"Engagée",RECEPTION!$W$4:$W$50000,"VALIDEE")) | F24: =IF(A24="","",D24+E24) | G24: =IF(A24="","",B24-F24) | H24: =IF(OR(A24="",N(B24)=0),"",F24/B24) | I24: =IF(A24="","",C24-D24) | J24: =IF(A24="","",COUNTIFS(RECEPTION!$F$4:$F$50000,A24,RECEPTION!$W$4:$W$50000,"A VERIFIER")) | K24: =IF(A24="","",COUNTIFS(RECEPTION!$F$4:$F$50000,A24,RECEPTION!$W$4:$W$50000,"REJETEE")) | L24: =IF(A24="","",IF(_xlfn.MAXIFS(JOURNAL_IMPORTS!$A$4:$A$5000,JOURNAL_IMPORTS!$C$4:$C$5000,A24)=0,"Aucune",_xlfn.MAXIFS(JOURNAL_IMPORTS!$A$4:$A$5000,JOURNAL_IMPORTS!$C$4:$C$5000,A24))) | N24: =IF(PARAMETRES!L23="","",PARAMETRES!L23) | O24: =IF(N24="","",SUMIFS(RECEPTION!$O$4:$O$50000,RECEPTION!$H$4:$H$50000,N24,RECEPTION!$M$4:$M$50000,"Payée",RECEPTION!$W$4:$W$50000,"VALIDEE")) | P24: =IF(N24="","",SUMIFS(RECEPTION!$O$4:$O$50000,RECEPTION!$H$4:$H$50000,N24,RECEPTION!$M$4:$M$50000,"Engagée",RECEPTION!$W$4:$W$50000,"VALIDEE")) | Q24: =IF(N24="","",O24+P24)
A25: =IF(PARAMETRES!E24="","",PARAMETRES!E24) | B25: =IF(A25="","",SUMIFS(BUDGETS_SERVICES!$E$4:$E$20000,BUDGETS_SERVICES!$A$4:$A$20000,A25)) | C25: =IF(A25="","",SUMIFS(RECEPTION!$N$4:$N$50000,RECEPTION!$F$4:$F$50000,A25,RECEPTION!$W$4:$W$50000,"VALIDEE")) | D25: =IF(A25="","",SUMIFS(RECEPTION!$O$4:$O$50000,RECEPTION!$F$4:$F$50000,A25,RECEPTION!$M$4:$M$50000,"Payée",RECEPTION!$W$4:$W$50000,"VALIDEE")) | E25: =IF(A25="","",SUMIFS(RECEPTION!$O$4:$O$50000,RECEPTION!$F$4:$F$50000,A25,RECEPTION!$M$4:$M$50000,"Engagée",RECEPTION!$W$4:$W$50000,"VALIDEE")) | F25: =IF(A25="","",D25+E25) | G25: =IF(A25="","",B25-F25) | H25: =IF(OR(A25="",N(B25)=0),"",F25/B25) | I25: =IF(A25="","",C25-D25) | J25: =IF(A25="","",COUNTIFS(RECEPTION!$F$4:$F$50000,A25,RECEPTION!$W$4:$W$50000,"A VERIFIER")) | K25: =IF(A25="","",COUNTIFS(RECEPTION!$F$4:$F$50000,A25,RECEPTION!$W$4:$W$50000,"REJETEE")) | L25: =IF(A25="","",IF(_xlfn.MAXIFS(JOURNAL_IMPORTS!$A$4:$A$5000,JOURNAL_IMPORTS!$C$4:$C$5000,A25)=0,"Aucune",_xlfn.MAXIFS(JOURNAL_IMPORTS!$A$4:$A$5000,JOURNAL_IMPORTS!$C$4:$C$5000,A25)))
A26: =IF(PARAMETRES!E25="","",PARAMETRES!E25) | B26: =IF(A26="","",SUMIFS(BUDGETS_SERVICES!$E$4:$E$20000,BUDGETS_SERVICES!$A$4:$A$20000,A26)) | C26: =IF(A26="","",SUMIFS(RECEPTION!$N$4:$N$50000,RECEPTION!$F$4:$F$50000,A26,RECEPTION!$W$4:$W$50000,"VALIDEE")) | D26: =IF(A26="","",SUMIFS(RECEPTION!$O$4:$O$50000,RECEPTION!$F$4:$F$50000,A26,RECEPTION!$M$4:$M$50000,"Payée",RECEPTION!$W$4:$W$50000,"VALIDEE")) | E26: =IF(A26="","",SUMIFS(RECEPTION!$O$4:$O$50000,RECEPTION!$F$4:$F$50000,A26,RECEPTION!$M$4:$M$50000,"Engagée",RECEPTION!$W$4:$W$50000,"VALIDEE")) | F26: =IF(A26="","",D26+E26) | G26: =IF(A26="","",B26-F26) | H26: =IF(OR(A26="",N(B26)=0),"",F26/B26) | I26: =IF(A26="","",C26-D26) | J26: =IF(A26="","",COUNTIFS(RECEPTION!$F$4:$F$50000,A26,RECEPTION!$W$4:$W$50000,"A VERIFIER")) | K26: =IF(A26="","",COUNTIFS(RECEPTION!$F$4:$F$50000,A26,RECEPTION!$W$4:$W$50000,"REJETEE")) | L26: =IF(A26="","",IF(_xlfn.MAXIFS(JOURNAL_IMPORTS!$A$4:$A$5000,JOURNAL_IMPORTS!$C$4:$C$5000,A26)=0,"Aucune",_xlfn.MAXIFS(JOURNAL_IMPORTS!$A$4:$A$5000,JOURNAL_IMPORTS!$C$4:$C$5000,A26)))
A27: =IF(PARAMETRES!E26="","",PARAMETRES!E26) | B27: =IF(A27="","",SUMIFS(BUDGETS_SERVICES!$E$4:$E$20000,BUDGETS_SERVICES!$A$4:$A$20000,A27)) | C27: =IF(A27="","",SUMIFS(RECEPTION!$N$4:$N$50000,RECEPTION!$F$4:$F$50000,A27,RECEPTION!$W$4:$W$50000,"VALIDEE")) | D27: =IF(A27="","",SUMIFS(RECEPTION!$O$4:$O$50000,RECEPTION!$F$4:$F$50000,A27,RECEPTION!$M$4:$M$50000,"Payée",RECEPTION!$W$4:$W$50000,"VALIDEE")) | E27: =IF(A27="","",SUMIFS(RECEPTION!$O$4:$O$50000,RECEPTION!$F$4:$F$50000,A27,RECEPTION!$M$4:$M$50000,"Engagée",RECEPTION!$W$4:$W$50000,"VALIDEE")) | F27: =IF(A27="","",D27+E27) | G27: =IF(A27="","",B27-F27) | H27: =IF(OR(A27="",N(B27)=0),"",F27/B27) | I27: =IF(A27="","",C27-D27) | J27: =IF(A27="","",COUNTIFS(RECEPTION!$F$4:$F$50000,A27,RECEPTION!$W$4:$W$50000,"A VERIFIER")) | K27: =IF(A27="","",COUNTIFS(RECEPTION!$F$4:$F$50000,A27,RECEPTION!$W$4:$W$50000,"REJETEE")) | L27: =IF(A27="","",IF(_xlfn.MAXIFS(JOURNAL_IMPORTS!$A$4:$A$5000,JOURNAL_IMPORTS!$C$4:$C$5000,A27)=0,"Aucune",_xlfn.MAXIFS(JOURNAL_IMPORTS!$A$4:$A$5000,JOURNAL_IMPORTS!$C$4:$C$5000,A27)))
A28: =IF(PARAMETRES!E27="","",PARAMETRES!E27) | B28: =IF(A28="","",SUMIFS(BUDGETS_SERVICES!$E$4:$E$20000,BUDGETS_SERVICES!$A$4:$A$20000,A28)) | C28: =IF(A28="","",SUMIFS(RECEPTION!$N$4:$N$50000,RECEPTION!$F$4:$F$50000,A28,RECEPTION!$W$4:$W$50000,"VALIDEE")) | D28: =IF(A28="","",SUMIFS(RECEPTION!$O$4:$O$50000,RECEPTION!$F$4:$F$50000,A28,RECEPTION!$M$4:$M$50000,"Payée",RECEPTION!$W$4:$W$50000,"VALIDEE")) | E28: =IF(A28="","",SUMIFS(RECEPTION!$O$4:$O$50000,RECEPTION!$F$4:$F$50000,A28,RECEPTION!$M$4:$M$50000,"Engagée",RECEPTION!$W$4:$W$50000,"VALIDEE")) | F28: =IF(A28="","",D28+E28) | G28: =IF(A28="","",B28-F28) | H28: =IF(OR(A28="",N(B28)=0),"",F28/B28) | I28: =IF(A28="","",C28-D28) | J28: =IF(A28="","",COUNTIFS(RECEPTION!$F$4:$F$50000,A28,RECEPTION!$W$4:$W$50000,"A VERIFIER")) | K28: =IF(A28="","",COUNTIFS(RECEPTION!$F$4:$F$50000,A28,RECEPTION!$W$4:$W$50000,"REJETEE")) | L28: =IF(A28="","",IF(_xlfn.MAXIFS(JOURNAL_IMPORTS!$A$4:$A$5000,JOURNAL_IMPORTS!$C$4:$C$5000,A28)=0,"Aucune",_xlfn.MAXIFS(JOURNAL_IMPORTS!$A$4:$A$5000,JOURNAL_IMPORTS!$C$4:$C$5000,A28)))
A29: =IF(PARAMETRES!E28="","",PARAMETRES!E28) | B29: =IF(A29="","",SUMIFS(BUDGETS_SERVICES!$E$4:$E$20000,BUDGETS_SERVICES!$A$4:$A$20000,A29)) | C29: =IF(A29="","",SUMIFS(RECEPTION!$N$4:$N$50000,RECEPTION!$F$4:$F$50000,A29,RECEPTION!$W$4:$W$50000,"VALIDEE")) | D29: =IF(A29="","",SUMIFS(RECEPTION!$O$4:$O$50000,RECEPTION!$F$4:$F$50000,A29,RECEPTION!$M$4:$M$50000,"Payée",RECEPTION!$W$4:$W$50000,"VALIDEE")) | E29: =IF(A29="","",SUMIFS(RECEPTION!$O$4:$O$50000,RECEPTION!$F$4:$F$50000,A29,RECEPTION!$M$4:$M$50000,"Engagée",RECEPTION!$W$4:$W$50000,"VALIDEE")) | F29: =IF(A29="","",D29+E29) | G29: =IF(A29="","",B29-F29) | H29: =IF(OR(A29="",N(B29)=0),"",F29/B29) | I29: =IF(A29="","",C29-D29) | J29: =IF(A29="","",COUNTIFS(RECEPTION!$F$4:$F$50000,A29,RECEPTION!$W$4:$W$50000,"A VERIFIER")) | K29: =IF(A29="","",COUNTIFS(RECEPTION!$F$4:$F$50000,A29,RECEPTION!$W$4:$W$50000,"REJETEE")) | L29: =IF(A29="","",IF(_xlfn.MAXIFS(JOURNAL_IMPORTS!$A$4:$A$5000,JOURNAL_IMPORTS!$C$4:$C$5000,A29)=0,"Aucune",_xlfn.MAXIFS(JOURNAL_IMPORTS!$A$4:$A$5000,JOURNAL_IMPORTS!$C$4:$C$5000,A29)))
A30: =IF(PARAMETRES!E29="","",PARAMETRES!E29) | B30: =IF(A30="","",SUMIFS(BUDGETS_SERVICES!$E$4:$E$20000,BUDGETS_SERVICES!$A$4:$A$20000,A30)) | C30: =IF(A30="","",SUMIFS(RECEPTION!$N$4:$N$50000,RECEPTION!$F$4:$F$50000,A30,RECEPTION!$W$4:$W$50000,"VALIDEE")) | D30: =IF(A30="","",SUMIFS(RECEPTION!$O$4:$O$50000,RECEPTION!$F$4:$F$50000,A30,RECEPTION!$M$4:$M$50000,"Payée",RECEPTION!$W$4:$W$50000,"VALIDEE")) | E30: =IF(A30="","",SUMIFS(RECEPTION!$O$4:$O$50000,RECEPTION!$F$4:$F$50000,A30,RECEPTION!$M$4:$M$50000,"Engagée",RECEPTION!$W$4:$W$50000,"VALIDEE")) | F30: =IF(A30="","",D30+E30) | G30: =IF(A30="","",B30-F30) | H30: =IF(OR(A30="",N(B30)=0),"",F30/B30) | I30: =IF(A30="","",C30-D30) | J30: =IF(A30="","",COUNTIFS(RECEPTION!$F$4:$F$50000,A30,RECEPTION!$W$4:$W$50000,"A VERIFIER")) | K30: =IF(A30="","",COUNTIFS(RECEPTION!$F$4:$F$50000,A30,RECEPTION!$W$4:$W$50000,"REJETEE")) | L30: =IF(A30="","",IF(_xlfn.MAXIFS(JOURNAL_IMPORTS!$A$4:$A$5000,JOURNAL_IMPORTS!$C$4:$C$5000,A30)=0,"Aucune",_xlfn.MAXIFS(JOURNAL_IMPORTS!$A$4:$A$5000,JOURNAL_IMPORTS!$C$4:$C$5000,A30)))
A31: =IF(PARAMETRES!E30="","",PARAMETRES!E30) | B31: =IF(A31="","",SUMIFS(BUDGETS_SERVICES!$E$4:$E$20000,BUDGETS_SERVICES!$A$4:$A$20000,A31)) | C31: =IF(A31="","",SUMIFS(RECEPTION!$N$4:$N$50000,RECEPTION!$F$4:$F$50000,A31,RECEPTION!$W$4:$W$50000,"VALIDEE")) | D31: =IF(A31="","",SUMIFS(RECEPTION!$O$4:$O$50000,RECEPTION!$F$4:$F$50000,A31,RECEPTION!$M$4:$M$50000,"Payée",RECEPTION!$W$4:$W$50000,"VALIDEE")) | E31: =IF(A31="","",SUMIFS(RECEPTION!$O$4:$O$50000,RECEPTION!$F$4:$F$50000,A31,RECEPTION!$M$4:$M$50000,"Engagée",RECEPTION!$W$4:$W$50000,"VALIDEE")) | F31: =IF(A31="","",D31+E31) | G31: =IF(A31="","",B31-F31) | H31: =IF(OR(A31="",N(B31)=0),"",F31/B31) | I31: =IF(A31="","",C31-D31) | J31: =IF(A31="","",COUNTIFS(RECEPTION!$F$4:$F$50000,A31,RECEPTION!$W$4:$W$50000,"A VERIFIER")) | K31: =IF(A31="","",COUNTIFS(RECEPTION!$F$4:$F$50000,A31,RECEPTION!$W$4:$W$50000,"REJETEE")) | L31: =IF(A31="","",IF(_xlfn.MAXIFS(JOURNAL_IMPORTS!$A$4:$A$5000,JOURNAL_IMPORTS!$C$4:$C$5000,A31)=0,"Aucune",_xlfn.MAXIFS(JOURNAL_IMPORTS!$A$4:$A$5000,JOURNAL_IMPORTS!$C$4:$C$5000,A31)))
A32: =IF(PARAMETRES!E31="","",PARAMETRES!E31) | B32: =IF(A32="","",SUMIFS(BUDGETS_SERVICES!$E$4:$E$20000,BUDGETS_SERVICES!$A$4:$A$20000,A32)) | C32: =IF(A32="","",SUMIFS(RECEPTION!$N$4:$N$50000,RECEPTION!$F$4:$F$50000,A32,RECEPTION!$W$4:$W$50000,"VALIDEE")) | D32: =IF(A32="","",SUMIFS(RECEPTION!$O$4:$O$50000,RECEPTION!$F$4:$F$50000,A32,RECEPTION!$M$4:$M$50000,"Payée",RECEPTION!$W$4:$W$50000,"VALIDEE")) | E32: =IF(A32="","",SUMIFS(RECEPTION!$O$4:$O$50000,RECEPTION!$F$4:$F$50000,A32,RECEPTION!$M$4:$M$50000,"Engagée",RECEPTION!$W$4:$W$50000,"VALIDEE")) | F32: =IF(A32="","",D32+E32) | G32: =IF(A32="","",B32-F32) | H32: =IF(OR(A32="",N(B32)=0),"",F32/B32) | I32: =IF(A32="","",C32-D32) | J32: =IF(A32="","",COUNTIFS(RECEPTION!$F$4:$F$50000,A32,RECEPTION!$W$4:$W$50000,"A VERIFIER")) | K32: =IF(A32="","",COUNTIFS(RECEPTION!$F$4:$F$50000,A32,RECEPTION!$W$4:$W$50000,"REJETEE")) | L32: =IF(A32="","",IF(_xlfn.MAXIFS(JOURNAL_IMPORTS!$A$4:$A$5000,JOURNAL_IMPORTS!$C$4:$C$5000,A32)=0,"Aucune",_xlfn.MAXIFS(JOURNAL_IMPORTS!$A$4:$A$5000,JOURNAL_IMPORTS!$C$4:$C$5000,A32)))
A33: =IF(PARAMETRES!E32="","",PARAMETRES!E32) | B33: =IF(A33="","",SUMIFS(BUDGETS_SERVICES!$E$4:$E$20000,BUDGETS_SERVICES!$A$4:$A$20000,A33)) | C33: =IF(A33="","",SUMIFS(RECEPTION!$N$4:$N$50000,RECEPTION!$F$4:$F$50000,A33,RECEPTION!$W$4:$W$50000,"VALIDEE")) | D33: =IF(A33="","",SUMIFS(RECEPTION!$O$4:$O$50000,RECEPTION!$F$4:$F$50000,A33,RECEPTION!$M$4:$M$50000,"Payée",RECEPTION!$W$4:$W$50000,"VALIDEE")) | E33: =IF(A33="","",SUMIFS(RECEPTION!$O$4:$O$50000,RECEPTION!$F$4:$F$50000,A33,RECEPTION!$M$4:$M$50000,"Engagée",RECEPTION!$W$4:$W$50000,"VALIDEE")) | F33: =IF(A33="","",D33+E33) | G33: =IF(A33="","",B33-F33) | H33: =IF(OR(A33="",N(B33)=0),"",F33/B33) | I33: =IF(A33="","",C33-D33) | J33: =IF(A33="","",COUNTIFS(RECEPTION!$F$4:$F$50000,A33,RECEPTION!$W$4:$W$50000,"A VERIFIER")) | K33: =IF(A33="","",COUNTIFS(RECEPTION!$F$4:$F$50000,A33,RECEPTION!$W$4:$W$50000,"REJETEE")) | L33: =IF(A33="","",IF(_xlfn.MAXIFS(JOURNAL_IMPORTS!$A$4:$A$5000,JOURNAL_IMPORTS!$C$4:$C$5000,A33)=0,"Aucune",_xlfn.MAXIFS(JOURNAL_IMPORTS!$A$4:$A$5000,JOURNAL_IMPORTS!$C$4:$C$5000,A33)))
A34: =IF(PARAMETRES!E33="","",PARAMETRES!E33) | B34: =IF(A34="","",SUMIFS(BUDGETS_SERVICES!$E$4:$E$20000,BUDGETS_SERVICES!$A$4:$A$20000,A34)) | C34: =IF(A34="","",SUMIFS(RECEPTION!$N$4:$N$50000,RECEPTION!$F$4:$F$50000,A34,RECEPTION!$W$4:$W$50000,"VALIDEE")) | D34: =IF(A34="","",SUMIFS(RECEPTION!$O$4:$O$50000,RECEPTION!$F$4:$F$50000,A34,RECEPTION!$M$4:$M$50000,"Payée",RECEPTION!$W$4:$W$50000,"VALIDEE")) | E34: =IF(A34="","",SUMIFS(RECEPTION!$O$4:$O$50000,RECEPTION!$F$4:$F$50000,A34,RECEPTION!$M$4:$M$50000,"Engagée",RECEPTION!$W$4:$W$50000,"VALIDEE")) | F34: =IF(A34="","",D34+E34) | G34: =IF(A34="","",B34-F34) | H34: =IF(OR(A34="",N(B34)=0),"",F34/B34) | I34: =IF(A34="","",C34-D34) | J34: =IF(A34="","",COUNTIFS(RECEPTION!$F$4:$F$50000,A34,RECEPTION!$W$4:$W$50000,"A VERIFIER")) | K34: =IF(A34="","",COUNTIFS(RECEPTION!$F$4:$F$50000,A34,RECEPTION!$W$4:$W$50000,"REJETEE")) | L34: =IF(A34="","",IF(_xlfn.MAXIFS(JOURNAL_IMPORTS!$A$4:$A$5000,JOURNAL_IMPORTS!$C$4:$C$5000,A34)=0,"Aucune",_xlfn.MAXIFS(JOURNAL_IMPORTS!$A$4:$A$5000,JOURNAL_IMPORTS!$C$4:$C$5000,A34)))
A35: =IF(PARAMETRES!E34="","",PARAMETRES!E34) | B35: =IF(A35="","",SUMIFS(BUDGETS_SERVICES!$E$4:$E$20000,BUDGETS_SERVICES!$A$4:$A$20000,A35)) | C35: =IF(A35="","",SUMIFS(RECEPTION!$N$4:$N$50000,RECEPTION!$F$4:$F$50000,A35,RECEPTION!$W$4:$W$50000,"VALIDEE")) | D35: =IF(A35="","",SUMIFS(RECEPTION!$O$4:$O$50000,RECEPTION!$F$4:$F$50000,A35,RECEPTION!$M$4:$M$50000,"Payée",RECEPTION!$W$4:$W$50000,"VALIDEE")) | E35: =IF(A35="","",SUMIFS(RECEPTION!$O$4:$O$50000,RECEPTION!$F$4:$F$50000,A35,RECEPTION!$M$4:$M$50000,"Engagée",RECEPTION!$W$4:$W$50000,"VALIDEE")) | F35: =IF(A35="","",D35+E35) | G35: =IF(A35="","",B35-F35) | H35: =IF(OR(A35="",N(B35)=0),"",F35/B35) | I35: =IF(A35="","",C35-D35) | J35: =IF(A35="","",COUNTIFS(RECEPTION!$F$4:$F$50000,A35,RECEPTION!$W$4:$W$50000,"A VERIFIER")) | K35: =IF(A35="","",COUNTIFS(RECEPTION!$F$4:$F$50000,A35,RECEPTION!$W$4:$W$50000,"REJETEE")) | L35: =IF(A35="","",IF(_xlfn.MAXIFS(JOURNAL_IMPORTS!$A$4:$A$5000,JOURNAL_IMPORTS!$C$4:$C$5000,A35)=0,"Aucune",_xlfn.MAXIFS(JOURNAL_IMPORTS!$A$4:$A$5000,JOURNAL_IMPORTS!$C$4:$C$5000,A35)))
A36: =IF(PARAMETRES!E35="","",PARAMETRES!E35) | B36: =IF(A36="","",SUMIFS(BUDGETS_SERVICES!$E$4:$E$20000,BUDGETS_SERVICES!$A$4:$A$20000,A36)) | C36: =IF(A36="","",SUMIFS(RECEPTION!$N$4:$N$50000,RECEPTION!$F$4:$F$50000,A36,RECEPTION!$W$4:$W$50000,"VALIDEE")) | D36: =IF(A36="","",SUMIFS(RECEPTION!$O$4:$O$50000,RECEPTION!$F$4:$F$50000,A36,RECEPTION!$M$4:$M$50000,"Payée",RECEPTION!$W$4:$W$50000,"VALIDEE")) | E36: =IF(A36="","",SUMIFS(RECEPTION!$O$4:$O$50000,RECEPTION!$F$4:$F$50000,A36,RECEPTION!$M$4:$M$50000,"Engagée",RECEPTION!$W$4:$W$50000,"VALIDEE")) | F36: =IF(A36="","",D36+E36) | G36: =IF(A36="","",B36-F36) | H36: =IF(OR(A36="",N(B36)=0),"",F36/B36) | I36: =IF(A36="","",C36-D36) | J36: =IF(A36="","",COUNTIFS(RECEPTION!$F$4:$F$50000,A36,RECEPTION!$W$4:$W$50000,"A VERIFIER")) | K36: =IF(A36="","",COUNTIFS(RECEPTION!$F$4:$F$50000,A36,RECEPTION!$W$4:$W$50000,"REJETEE")) | L36: =IF(A36="","",IF(_xlfn.MAXIFS(JOURNAL_IMPORTS!$A$4:$A$5000,JOURNAL_IMPORTS!$C$4:$C$5000,A36)=0,"Aucune",_xlfn.MAXIFS(JOURNAL_IMPORTS!$A$4:$A$5000,JOURNAL_IMPORTS!$C$4:$C$5000,A36)))
... A44: =IF(PARAMETRES!E43="","",PARAMETRES!E43) | B44: =IF(A44="","",SUMIFS(BUDGETS_SERVICES!$E$4:$E$20000,BUDGETS_SERVICES!$A$4:$A$20000,A44)) | C44: =IF(A44="","",SUMIFS(RECEPTION!$N$4:$N$50000,RECEPTION!$F$4:$F$50000,A44,RECEPTION!$W$4:$W$50000,"VALIDEE")) | D44: =IF(A44="","",SUMIFS(RECEPTION!$O$4:$O$50000,RECEPTION!$F$4:$F$50000,A44,RECEPTION!$M$4:$M$50000,"Payée",RECEPTION!$W$4:$W$50000,"VALIDEE")) | E44: =IF(A44="","",SUMIFS(RECEPTION!$O$4:$O$50000,RECEPTION!$F$4:$F$50000,A44,RECEPTION!$M$4:$M$50000,"Engagée",RECEPTION!$W$4:$W$50000,"VALIDEE")) | F44: =IF(A44="","",D44+E44) | G44: =IF(A44="","",B44-F44) | H44: =IF(OR(A44="",N(B44)=0),"",F44/B44) | I44: =IF(A44="","",C44-D44) | J44: =IF(A44="","",COUNTIFS(RECEPTION!$F$4:$F$50000,A44,RECEPTION!$W$4:$W$50000,"A VERIFIER")) | K44: =IF(A44="","",COUNTIFS(RECEPTION!$F$4:$F$50000,A44,RECEPTION!$W$4:$W$50000,"REJETEE")) | L44: =IF(A44="","",IF(_xlfn.MAXIFS(JOURNAL_IMPORTS!$A$4:$A$5000,JOURNAL_IMPORTS!$C$4:$C$5000,A44)=0,"Aucune",_xlfn.MAXIFS(JOURNAL_IMPORTS!$A$4:$A$5000,JOURNAL_IMPORTS!$C$4:$C$5000,A44)))

Sheet TABLEAU_DE_BORD
B1: ="TABLEAU DE BORD GÉNÉRAL — Exercice "&C_EXERCICE
B2: Écritures validées uniquement. Actualiser après chaque import / validation.
B4: Budget total | C4: Total consommé | D4: Disponible | E4: Taux d'exécution | F4: Entrées (approvisionnements)
B5: =CONSOLIDATION!B4 | C5: =CONSOLIDATION!F4 | D5: =CONSOLIDATION!G4 | E5: =IF(CONSOLIDATION!B4=0,"",CONSOLIDATION!F4/CONSOLIDATION!B4) | F5: =CONSOLIDATION!C4
B7: Solde de caisse consolidé | C7: Services ayant transmis | D7: Écritures à vérifier | E7: Écritures avec anomalie | F7: Écritures rejetées
B8: =CONSOLIDATION!I4 | C8: =COUNT(CONSOLIDATION!L5:L44)&" / "&COUNTIF(CONSOLIDATION!A5:A44,"?*") | D8: =CONSOLIDATION!J4 | E8: =VERIFICATION!B7 | F8: =CONSOLIDATION!K4

Sheet BUDGETS_SERVICES
A1: BUDGETS DES SERVICES (reçus avec les transmissions)
A2: Remplacés à chaque transmission du service concerné.
A3: Service | B3: Code rubrique | C3: Libellé rubrique | D3: Catégorie | E3: Budget annuel (CDF) | F3: ID_TRANSMISSION | G3: Date de réception

Sheet JOURNAL_IMPORTS
A1: JOURNAL DES IMPORTS
A2: Un fichier déjà présent dans ce journal n'est jamais réimporté.
A3: Date import | B3: Fichier | C3: Service | D3: ID_TRANSMISSION | E3: Lignes annoncées | F3: Lignes lues | G3: Nouvelles | H3: Mises à jour | I3: Doublons ignorés | J3: Importé par | K3: Résultat

Sheet PARAMETRES
A1: PARAMÈTRES DU CLASSEUR CENTRAL
A2: Cellules jaunes à compléter. Les chemins sont des exemples à remplacer.
B3: Libellé | C3: Valeur | E3: Code service | F3: Libellé du service | G3: Nom du fichier de service | I3: Profils | J3: Actif | K3: États de vérification | L3: Catégories
B4: Institution | C4: Inspection Générale des Finances (IGE) | E4: 8000 IG | F4: 8000 IG | G4: =IF(E4="","","SERVICE_"&SUBSTITUTE(E4," ","_")&".xlsm") | I4: AGENT | J4: OUI | K4: A VERIFIER | L4: Fournitures et petits matériels
B5: Exercice | C5: 2026 | E5: 8000 IGA | F5: 8000 IGA | G5: =IF(E5="","","SERVICE_"&SUBSTITUTE(E5," ","_")&".xlsm") | I5: RESPONSABLE | J5: NON | K5: VALIDEE | L5: Carburant et lubrifiants
B6: Dossier de transmission | C6: \\SERVEUR-IGE\IGE_FF\TRANSMISSIONS\ | E6: 8000C OF | F6: 8000C OF | G6: =IF(E6="","","SERVICE_"&SUBSTITUTE(E6," ","_")&".xlsm") | I6: ADMIN | K6: REJETEE | L6: Entretien et réparation
B7: Préfixe des fichiers de transmission | C7: TRANS_ | E7: 8000C DD | F7: 8000C DD | G7: =IF(E7="","","SERVICE_"&SUBSTITUTE(E7," ","_")&".xlsm") | L7: Communication et internet
B8: Fichier modèle de service (.xlsm) | C8: \\SERVEUR-IGE\IGE_FF\MODELE\IGE_FF_SERVICE_MODELE.xlsm | E8: 8000C CAJ | F8: 8000C CAJ | G8: =IF(E8="","","SERVICE_"&SUBSTITUTE(E8," ","_")&".xlsm") | L8: Transport et déplacements
B9: Dossier de sortie des fichiers services | C9: \\SERVEUR-IGE\IGE_FF\SERVICES\ | E9: 8000C PP | F9: 8000C PP | G9: =IF(E9="","","SERVICE_"&SUBSTITUTE(E9," ","_")&".xlsm") | L9: Restauration et réception
B10: Service d'administration | C10: ADMINISTRATION ET FINANCE | E10: 8001 | F10: 8001 | G10: =IF(E10="","","SERVICE_"&SUBSTITUTE(E10," ","_")&".xlsm") | L10: Frais bancaires
E11: 8002 | F11: 8002 | G11: =IF(E11="","","SERVICE_"&SUBSTITUTE(E11," ","_")&".xlsm") | L11: Divers
E12: 8003 | F12: 8003 | G12: =IF(E12="","","SERVICE_"&SUBSTITUTE(E12," ","_")&".xlsm")
E13: 8004 | F13: 8004 | G13: =IF(E13="","","SERVICE_"&SUBSTITUTE(E13," ","_")&".xlsm")
E14: 8005 | F14: 8005 | G14: =IF(E14="","","SERVICE_"&SUBSTITUTE(E14," ","_")&".xlsm")
E15: 8006 | F15: 8006 | G15: =IF(E15="","","SERVICE_"&SUBSTITUTE(E15," ","_")&".xlsm")
E16: 8007 | F16: 8007 | G16: =IF(E16="","","SERVICE_"&SUBSTITUTE(E16," ","_")&".xlsm")
E17: 8008 | F17: 8008 | G17: =IF(E17="","","SERVICE_"&SUBSTITUTE(E17," ","_")&".xlsm")
E18: 8009 | F18: 8009 | G18: =IF(E18="","","SERVICE_"&SUBSTITUTE(E18," ","_")&".xlsm")
E19: 8010 | F19: 8010 | G19: =IF(E19="","","SERVICE_"&SUBSTITUTE(E19," ","_")&".xlsm")
E20: 8011 | F20: 8011 | G20: =IF(E20="","","SERVICE_"&SUBSTITUTE(E20," ","_")&".xlsm")
E21: 8012 | F21: 8012 | G21: =IF(E21="","","SERVICE_"&SUBSTITUTE(E21," ","_")&".xlsm")
E22: 8013 | F22: 8013 | G22: =IF(E22="","","SERVICE_"&SUBSTITUTE(E22," ","_")&".xlsm")
E23: 8014 | F23: 8014 | G23: =IF(E23="","","SERVICE_"&SUBSTITUTE(E23," ","_")&".xlsm")
... E32: Communication | F32: Communication | G32: =IF(E32="","","SERVICE_"&SUBSTITUTE(E32," ","_")&".xlsm")
G33: =IF(E33="","","SERVICE_"&SUBSTITUTE(E33," ","_")&".xlsm")
G34: =IF(E34="","","SERVICE_"&SUBSTITUTE(E34," ","_")&".xlsm")
G35: =IF(E35="","","SERVICE_"&SUBSTITUTE(E35," ","_")&".xlsm")
G36: =IF(E36="","","SERVICE_"&SUBSTITUTE(E36," ","_")&".xlsm")
G37: =IF(E37="","","SERVICE_"&SUBSTITUTE(E37," ","_")&".xlsm")
G38: =IF(E38="","","SERVICE_"&SUBSTITUTE(E38," ","_")&".xlsm")
G39: =IF(E39="","","SERVICE_"&SUBSTITUTE(E39," ","_")&".xlsm")
G40: =IF(E40="","","SERVICE_"&SUBSTITUTE(E40," ","_")&".xlsm")
G41: =IF(E41="","","SERVICE_"&SUBSTITUTE(E41," ","_")&".xlsm")
G42: =IF(E42="","","SERVICE_"&SUBSTITUTE(E42," ","_")&".xlsm")
G43: =IF(E43="","","SERVICE_"&SUBSTITUTE(E43," ","_")&".xlsm")

Sheet UTILISATEURS
A1: TABLE DES UTILISATEURS (tous services)
A2: Saisir le mot de passe initial en colonne H puis cliquer sur CHIFFRER LES MOTS DE PASSE : il est remplacé par son empreinte et effacé.
A3: Identifiant | B3: Empreinte du mot de passe | C3: Service attribué | D3: Profil | E3: Actif | F3: Changer MDP au prochain accès | G3: Dernière connexion | H3: Mot de passe initial (temporaire)
A4: admin.af | C4: ADMINISTRATION ET FINANCE | D4: ADMIN | E4: OUI | F4: OUI | H4: à définir
A5: agent8000 | C5: 8000 IG | D5: AGENT | E5: OUI | F5: OUI | H5: à définir
A6: resp8000 | C6: 8000 IG | D6: RESPONSABLE | E6: OUI | F6: OUI | H6: à définir

Sheet NOTICE
A1: NOTICE D'INSTALLATION ET D'EXPLOITATION
A3: A. INSTALLATION (une seule fois, par la personne qui administre le logiciel)
A4: 1. Ouvrir IGE_FF_SERVICE_MODELE.xlsx, Alt+F11, Fichier > Importer : modSecurite.bas, modService.bas.
A5: 2. Double-cliquer sur ThisWorkbook et coller le contenu de ThisWorkbook_SERVICE.txt.
A6: 3. Exécuter la macro INSTALLER_INTERFACE_SERVICE (Alt+F8) : création des boutons et protection des feuilles.
A7: 4. Outils > Propriétés de VBAProject > Protection : verrouiller le projet par un mot de passe.
A8: 5. Enregistrer sous IGE_FF_SERVICE_MODELE.xlsm (Classeur Excel prenant en charge les macros) dans le dossier MODELE.
A9: 6. Faire de même avec ce classeur : importer modSecurite.bas et modCentral.bas, coller ThisWorkbook_CENTRAL.txt,
A10: exécuter INSTALLER_INTERFACE_CENTRAL, protéger le projet VBA, enregistrer sous IGE_FF_CENTRAL.xlsm.
A11: 7. Changer la constante MDP_PROTECTION dans modSecurite (même valeur dans les deux fichiers) AVANT l'étape 3.
A13: B. DOSSIERS RÉSEAU (à faire avec l'informaticien)
A14: - \\SERVEUR\IGE_FF\CENTRAL : classeur central — accès Administration et Finance uniquement.
... A34: repose sur les droits NTFS des dossiers. Les mots de passe sont stockés sous forme d'empreinte, jamais en clair.
