Workbook
Name L_CATEGORIES: OFFSET(PARAMETRES!$I$4,0,0,MAX(1,COUNTA(PARAMETRES!$I$4:$I$23)),1)
Name L_MODES: PARAMETRES!$E$4:$E$7
Name L_MOIS: PARAMETRES!$H$4:$H$15
Name L_RUBRIQUES: OFFSET(BUDGET!$A$4,0,0,MAX(1,COUNTA(BUDGET!$A$4:$A$13)),1)
Name L_STATUTS: PARAMETRES!$F$4:$F$5
Name L_TYPES: PARAMETRES!$G$4:$G$5
Name P_CODE_SERVICE: PARAMETRES!$C$5
Name P_DERNIER_NUM: PARAMETRES!$C$12
Name P_DERNIER_TRANS: PARAMETRES!$C$13
Name P_DEVISE: PARAMETRES!$C$8
Name P_DOSSIER_TRANS: PARAMETRES!$C$10
Name P_EXERCICE: PARAMETRES!$C$7
Name P_INSTITUTION: PARAMETRES!$C$4
Name P_LIBELLE_SERVICE: PARAMETRES!$C$6
Name P_PREFIXE: PARAMETRES!$C$11
Name P_SOLDE_INITIAL: PARAMETRES!$C$9
Name P_VERSION: PARAMETRES!$C$14
Name S_HEURE: ACCUEIL!$I$7
Name S_PROFIL: ACCUEIL!$I$6
Name S_UTILISATEUR: ACCUEIL!$I$5

Sheet ACCUEIL
H2: GESTION DES FRAIS DE FONCTIONNEMENT | K2: Commandes
H4: Service | I4: =P_CODE_SERVICE&" — "&P_LIBELLE_SERVICE
H5: Utilisateur connecté
H6: Profil
H7: Connecté depuis

Sheet FORMULAIRE_SAISIE
B1: FORMULAIRE DE SAISIE DES ÉCRITURES
B4: N° de l'écriture | C4: ="Prochain N° : "&(P_DERNIER_NUM+1)
B5: Date de l'opération *
B6: Exercice | C6: =IF(C5="","",YEAR(C5))
B7: Mois | C7: =IF(C5="","",INDEX(L_MOIS,MONTH(C5)))
B8: Service | C8: =P_CODE_SERVICE
B9: Code rubrique *
B10: Libellé rubrique | C10: =IFERROR(INDEX(BUDGET!$B$4:$B$13,MATCH(C9,BUDGET!$A$4:$A$13,0)),"")
B11: Catégorie | C11: =IFERROR(INDEX(BUDGET!$C$4:$C$13,MATCH(C9,BUDGET!$A$4:$A$13,0)),"")
B12: Description *
B13: Fournisseur / bénéficiaire
B14: N° pièce justificative (obligatoire si sortie)
B15: Mode de paiement *
B16: Statut *
B17: Type d'opération *
B18: Montant (CDF) *
B19: Observations
B21: Saisi par | C21: =IF(S_UTILISATEUR="","(non connecté)",S_UTILISATEUR)
B22: Solde de caisse actuel | C22: =P_SOLDE_INITIAL+SUM(LIVRE_DE_CAISSE!$N$4:$N$4701)-SUMIFS(LIVRE_DE_CAISSE!$O$4:$O$4701,LIVRE_DE_CAISSE!$M$4:$M$4701,"Payée")
B23: Disponible sur la rubrique | C23: =IF(C9="","",IFERROR(INDEX(SUIVI_BUDGETAIRE!$H$5:$H$14,MATCH(C9,SUIVI_BUDGETAIRE!$A$5:$A$14,0)),""))
B25: * champ obligatoire. Une entrée (approvisionnement) est toujours enregistrée avec le statut « Payée ».

Sheet LIVRE_DE_CAISSE
A1: LIVRE DE CAISSE (CDF)
O2: Solde initial : | P2: 1000000
A3: ID_ECRITURE | B3: N° | C3: Date | D3: Exercice | E3: Mois | F3: Service | G3: Code rubrique | H3: Catégorie | I3: Description | J3: Fournisseur / bénéficiaire | K3: N° pièce | L3: Mode de paiement | M3: Statut | N3: Entrée | O3: Sortie | P3: Solde | Q3: Utilisateur | R3: Date de saisie | S3: Observations | T3: ID_TRANSMISSION | U3: ETAT_TRANSMISSION
A4: 9990TEST-2026-000001 | B4: 1 | C4: 46027 | D4: 2026 | F4: 9990 TEST | I4: Dotation janvier | L4: Virement | M4: Payée | N4: 5000000 | T4: TR-X | U4: TRANSMISE
A5: 9990TEST-2026-000002 | B5: 2 | C5: 46032 | D5: 2026 | F5: 9990 TEST | G5: R01 | I5: Ramettes de papier | J5: Papeterie Kin | K5: FAC-01 | L5: Espèces | M5: Payée | O5: 250000 | T5: TR-X | U5: TRANSMISE
A6: 9990TEST-2026-000003 | B6: 3 | C6: 46034 | D6: 2026 | F6: 9990 TEST | G6: R03 | I6: Carburant | J6: Station Gombe | L6: Espèces | M6: Payée | O6: 400000 | T6: TR-X | U6: TRANSMISE
A7: 9990TEST-2026-000004 | B7: 4 | C7: 46042 | D7: 2026 | F7: 9990 TEST | G7: R03 | I7: Contrepassation de 9990TEST-2026-000003 : pièce manquante | L7: Espèces | M7: Payée | O7: -400000 | U7: A TRANSMETTRE
A8: 9990TEST-2026-000005 | B8: 5 | C8: 46054 | D8: 2026 | F8: 9990 TEST | G8: R04 | I8: Révision véhicule | J8: Garage Lemba | K8: PRO-7 | L8: Cash | M8: Engagée | O8: 300000
A9: 9990TEST-2026-000006 | B9: 6 | C9: 15/02/2026 | D9: 2026 | F9: 9990 TEST | G9: R02 | I9: Toner imprimante | J9: Info Plus | K9: FAC-88 | L9: Espèces | M9: Payée | O9: 120000 | Q9: agent8000b | T9: TR-X | U9: TRANSMISE

Sheet BUDGET
A1: BUDGET ANNUEL DU SERVICE (CDF)
A3: Code rubrique | B3: Libellé rubrique | C3: Catégorie | D3: Budget annuel (CDF) | E3: Observations | G3: Total budget
A4: R01 | B4: Fournitures de bureau | C4: Fournitures et petits matériels | D4: 6000000 | G4: =SUM(D4:D13)
A5: R02 | B5: Consommables informatiques | C5: Fournitures et petits matériels | D5: 6000000
A6: R03 | B6: Carburant véhicules de service | C6: Carburant et lubrifiants | D6: 3000000
A7: R04 | B7: Entretien des véhicules | C7: Entretien et réparation | D7: 0
A8: R05 | B8: Entretien des locaux | C8: Entretien et réparation | D8: 1200000
A9: R06 | B9: Crédit téléphonique et internet | C9: Communication et internet | D9: 2800000
A10: R07 | B10: Frais de mission et transport | C10: Transport et déplacements | D10: 4000000
A11: R08 | B11: Réception et restauration | C11: Divers | D11: 5000000
A12: R09 | B12: Frais bancaires | C12: Divers | D12: 0
A13: R10 | B13: Dépenses diverses | C13: Divers | D13: 800000

Sheet SUIVI_BUDGETAIRE
A1: SUIVI BUDGÉTAIRE DU SERVICE (CDF)
A3: Code rubrique | B3: Libellé rubrique | C3: Catégorie | D3: Budget annuel | E3: Engagé (non payé) | F3: Payé | G3: Total consommé | H3: Disponible | I3: Taux d'exécution | K3: Mois | L3: Entrées | M3: Sorties payées | N3: Engagements
A4: TOTAL | D4: =SUM(D5:D14) | E4: =SUM(E5:E14) | F4: =SUM(F5:F14) | G4: =SUM(G5:G14) | H4: =SUM(H5:H14) | I4: =IF(D4=0,"",G4/D4) | K4: TOTAL | L4: =SUM(L5:L16) | M4: =SUM(M5:M16) | N4: =SUM(N5:N16)
A5: =IF(BUDGET!A4="","",BUDGET!A4) | B5: =IF(A5="","",BUDGET!B4) | C5: =IF(A5="","",BUDGET!C4) | D5: =IF(A5="","",N(BUDGET!D4)) | E5: =IF(A5="","",SUMIFS(LIVRE_DE_CAISSE!$O$4:$O$4701,LIVRE_DE_CAISSE!$G$4:$G$4701,A5,LIVRE_DE_CAISSE!$M$4:$M$4701,"Engagée")) | F5: =IF(A5="","",SUMIFS(LIVRE_DE_CAISSE!$O$4:$O$4701,LIVRE_DE_CAISSE!$G$4:$G$4701,A5,LIVRE_DE_CAISSE!$M$4:$M$4701,"Payée")) | G5: =IF(A5="","",E5+F5) | H5: =IF(A5="","",D5-G5) | I5: =IF(OR(A5="",N(D5)=0),"",G5/D5) | K5: =PARAMETRES!H4 | L5: =SUMIFS(LIVRE_DE_CAISSE!$N$4:$N$4701,LIVRE_DE_CAISSE!$E$4:$E$4701,K5) | M5: =SUMIFS(LIVRE_DE_CAISSE!$O$4:$O$4701,LIVRE_DE_CAISSE!$E$4:$E$4701,K5,LIVRE_DE_CAISSE!$M$4:$M$4701,"Payée") | N5: =SUMIFS(LIVRE_DE_CAISSE!$O$4:$O$4701,LIVRE_DE_CAISSE!$E$4:$E$4701,K5,LIVRE_DE_CAISSE!$M$4:$M$4701,"Engagée")
A6: =IF(BUDGET!A5="","",BUDGET!A5) | B6: =IF(A6="","",BUDGET!B5) | C6: =IF(A6="","",BUDGET!C5) | D6: =IF(A6="","",N(BUDGET!D5)) | E6: =IF(A6="","",SUMIFS(LIVRE_DE_CAISSE!$O$4:$O$4701,LIVRE_DE_CAISSE!$G$4:$G$4701,A6,LIVRE_DE_CAISSE!$M$4:$M$4701,"Engagée")) | F6: =IF(A6="","",SUMIFS(LIVRE_DE_CAISSE!$O$4:$O$4701,LIVRE_DE_CAISSE!$G$4:$G$4701,A6,LIVRE_DE_CAISSE!$M$4:$M$4701,"Payée")) | G6: =IF(A6="","",E6+F6) | H6: =IF(A6="","",D6-G6) | I6: =IF(OR(A6="",N(D6)=0),"",G6/D6) | K6: =PARAMETRES!H5 | L6: =SUMIFS(LIVRE_DE_CAISSE!$N$4:$N$4701,LIVRE_DE_CAISSE!$E$4:$E$4701,K6) | M6: =SUMIFS(LIVRE_DE_CAISSE!$O$4:$O$4701,LIVRE_DE_CAISSE!$E$4:$E$4701,K6,LIVRE_DE_CAISSE!$M$4:$M$4701,"Payée") | N6: =SUMIFS(LIVRE_DE_CAISSE!$O$4:$O$4701,LIVRE_DE_CAISSE!$E$4:$E$4701,K6,LIVRE_DE_CAISSE!$M$4:$M$4701,"Engagée")
A7: =IF(BUDGET!A6="","",BUDGET!A6) | B7: =IF(A7="","",BUDGET!B6) | C7: =IF(A7="","",BUDGET!C6) | D7: =IF(A7="","",N(BUDGET!D6)) | E7: =IF(A7="","",SUMIFS(LIVRE_DE_CAISSE!$O$4:$O$4701,LIVRE_DE_CAISSE!$G$4:$G$4701,A7,LIVRE_DE_CAISSE!$M$4:$M$4701,"Engagée")) | F7: =IF(A7="","",SUMIFS(LIVRE_DE_CAISSE!$O$4:$O$4701,LIVRE_DE_CAISSE!$G$4:$G$4701,A7,LIVRE_DE_CAISSE!$M$4:$M$4701,"Payée")) | G7: =IF(A7="","",E7+F7) | H7: =IF(A7="","",D7-G7) | I7: =IF(OR(A7="",N(D7)=0),"",G7/D7) | K7: =PARAMETRES!H6 | L7: =SUMIFS(LIVRE_DE_CAISSE!$N$4:$N$4701,LIVRE_DE_CAISSE!$E$4:$E$4701,K7) | M7: =SUMIFS(LIVRE_DE_CAISSE!$O$4:$O$4701,LIVRE_DE_CAISSE!$E$4:$E$4701,K7,LIVRE_DE_CAISSE!$M$4:$M$4701,"Payée") | N7: =SUMIFS(LIVRE_DE_CAISSE!$O$4:$O$4701,LIVRE_DE_CAISSE!$E$4:$E$4701,K7,LIVRE_DE_CAISSE!$M$4:$M$4701,"Engagée")
A8: =IF(BUDGET!A7="","",BUDGET!A7) | B8: =IF(A8="","",BUDGET!B7) | C8: =IF(A8="","",BUDGET!C7) | D8: =IF(A8="","",N(BUDGET!D7)) | E8: =IF(A8="","",SUMIFS(LIVRE_DE_CAISSE!$O$4:$O$4701,LIVRE_DE_CAISSE!$G$4:$G$4701,A8,LIVRE_DE_CAISSE!$M$4:$M$4701,"Engagée")) | F8: =IF(A8="","",SUMIFS(LIVRE_DE_CAISSE!$O$4:$O$4701,LIVRE_DE_CAISSE!$G$4:$G$4701,A8,LIVRE_DE_CAISSE!$M$4:$M$4701,"Payée")) | G8: =IF(A8="","",E8+F8) | H8: =IF(A8="","",D8-G8) | I8: =IF(OR(A8="",N(D8)=0),"",G8/D8) | K8: =PARAMETRES!H7 | L8: =SUMIFS(LIVRE_DE_CAISSE!$N$4:$N$4701,LIVRE_DE_CAISSE!$E$4:$E$4701,K8) | M8: =SUMIFS(LIVRE_DE_CAISSE!$O$4:$O$4701,LIVRE_DE_CAISSE!$E$4:$E$4701,K8,LIVRE_DE_CAISSE!$M$4:$M$4701,"Payée") | N8: =SUMIFS(LIVRE_DE_CAISSE!$O$4:$O$4701,LIVRE_DE_CAISSE!$E$4:$E$4701,K8,LIVRE_DE_CAISSE!$M$4:$M$4701,"Engagée")
A9: =IF(BUDGET!A8="","",BUDGET!A8) | B9: =IF(A9="","",BUDGET!B8) | C9: =IF(A9="","",BUDGET!C8) | D9: =IF(A9="","",N(BUDGET!D8)) | E9: =IF(A9="","",SUMIFS(LIVRE_DE_CAISSE!$O$4:$O$4701,LIVRE_DE_CAISSE!$G$4:$G$4701,A9,LIVRE_DE_CAISSE!$M$4:$M$4701,"Engagée")) | F9: =IF(A9="","",SUMIFS(LIVRE_DE_CAISSE!$O$4:$O$4701,LIVRE_DE_CAISSE!$G$4:$G$4701,A9,LIVRE_DE_CAISSE!$M$4:$M$4701,"Payée")) | G9: =IF(A9="","",E9+F9) | H9: =IF(A9="","",D9-G9) | I9: =IF(OR(A9="",N(D9)=0),"",G9/D9) | K9: =PARAMETRES!H8 | L9: =SUMIFS(LIVRE_DE_CAISSE!$N$4:$N$4701,LIVRE_DE_CAISSE!$E$4:$E$4701,K9) | M9: =SUMIFS(LIVRE_DE_CAISSE!$O$4:$O$4701,LIVRE_DE_CAISSE!$E$4:$E$4701,K9,LIVRE_DE_CAISSE!$M$4:$M$4701,"Payée") | N9: =SUMIFS(LIVRE_DE_CAISSE!$O$4:$O$4701,LIVRE_DE_CAISSE!$E$4:$E$4701,K9,LIVRE_DE_CAISSE!$M$4:$M$4701,"Engagée")
A10: =IF(BUDGET!A9="","",BUDGET!A9) | B10: =IF(A10="","",BUDGET!B9) | C10: =IF(A10="","",BUDGET!C9) | D10: =IF(A10="","",N(BUDGET!D9)) | E10: =IF(A10="","",SUMIFS(LIVRE_DE_CAISSE!$O$4:$O$4701,LIVRE_DE_CAISSE!$G$4:$G$4701,A10,LIVRE_DE_CAISSE!$M$4:$M$4701,"Engagée")) | F10: =IF(A10="","",SUMIFS(LIVRE_DE_CAISSE!$O$4:$O$4701,LIVRE_DE_CAISSE!$G$4:$G$4701,A10,LIVRE_DE_CAISSE!$M$4:$M$4701,"Payée")) | G10: =IF(A10="","",E10+F10) | H10: =IF(A10="","",D10-G10) | I10: =IF(OR(A10="",N(D10)=0),"",G10/D10) | K10: =PARAMETRES!H9 | L10: =SUMIFS(LIVRE_DE_CAISSE!$N$4:$N$4701,LIVRE_DE_CAISSE!$E$4:$E$4701,K10) | M10: =SUMIFS(LIVRE_DE_CAISSE!$O$4:$O$4701,LIVRE_DE_CAISSE!$E$4:$E$4701,K10,LIVRE_DE_CAISSE!$M$4:$M$4701,"Payée") | N10: =SUMIFS(LIVRE_DE_CAISSE!$O$4:$O$4701,LIVRE_DE_CAISSE!$E$4:$E$4701,K10,LIVRE_DE_CAISSE!$M$4:$M$4701,"Engagée")
A11: =IF(BUDGET!A10="","",BUDGET!A10) | B11: =IF(A11="","",BUDGET!B10) | C11: =IF(A11="","",BUDGET!C10) | D11: =IF(A11="","",N(BUDGET!D10)) | E11: =IF(A11="","",SUMIFS(LIVRE_DE_CAISSE!$O$4:$O$4701,LIVRE_DE_CAISSE!$G$4:$G$4701,A11,LIVRE_DE_CAISSE!$M$4:$M$4701,"Engagée")) | F11: =IF(A11="","",SUMIFS(LIVRE_DE_CAISSE!$O$4:$O$4701,LIVRE_DE_CAISSE!$G$4:$G$4701,A11,LIVRE_DE_CAISSE!$M$4:$M$4701,"Payée")) | G11: =IF(A11="","",E11+F11) | H11: =IF(A11="","",D11-G11) | I11: =IF(OR(A11="",N(D11)=0),"",G11/D11) | K11: =PARAMETRES!H10 | L11: =SUMIFS(LIVRE_DE_CAISSE!$N$4:$N$4701,LIVRE_DE_CAISSE!$E$4:$E$4701,K11) | M11: =SUMIFS(LIVRE_DE_CAISSE!$O$4:$O$4701,LIVRE_DE_CAISSE!$E$4:$E$4701,K11,LIVRE_DE_CAISSE!$M$4:$M$4701,"Payée") | N11: =SUMIFS(LIVRE_DE_CAISSE!$O$4:$O$4701,LIVRE_DE_CAISSE!$E$4:$E$4701,K11,LIVRE_DE_CAISSE!$M$4:$M$4701,"Engagée")
A12: =IF(BUDGET!A11="","",BUDGET!A11) | B12: =IF(A12="","",BUDGET!B11) | C12: =IF(A12="","",BUDGET!C11) | D12: =IF(A12="","",N(BUDGET!D11)) | E12: =IF(A12="","",SUMIFS(LIVRE_DE_CAISSE!$O$4:$O$4701,LIVRE_DE_CAISSE!$G$4:$G$4701,A12,LIVRE_DE_CAISSE!$M$4:$M$4701,"Engagée")) | F12: =IF(A12="","",SUMIFS(LIVRE_DE_CAISSE!$O$4:$O$4701,LIVRE_DE_CAISSE!$G$4:$G$4701,A12,LIVRE_DE_CAISSE!$M$4:$M$4701,"Payée")) | G12: =IF(A12="","",E12+F12) | H12: =IF(A12="","",D12-G12) | I12: =IF(OR(A12="",N(D12)=0),"",G12/D12) | K12: =PARAMETRES!H11 | L12: =SUMIFS(LIVRE_DE_CAISSE!$N$4:$N$4701,LIVRE_DE_CAISSE!$E$4:$E$4701,K12) | M12: =SUMIFS(LIVRE_DE_CAISSE!$O$4:$O$4701,LIVRE_DE_CAISSE!$E$4:$E$4701,K12,LIVRE_DE_CAISSE!$M$4:$M$4701,"Payée") | N12: =SUMIFS(LIVRE_DE_CAISSE!$O$4:$O$4701,LIVRE_DE_CAISSE!$E$4:$E$4701,K12,LIVRE_DE_CAISSE!$M$4:$M$4701,"Engagée")
A13: =IF(BUDGET!A12="","",BUDGET!A12) | B13: =IF(A13="","",BUDGET!B12) | C13: =IF(A13="","",BUDGET!C12) | D13: =IF(A13="","",N(BUDGET!D12)) | E13: =IF(A13="","",SUMIFS(LIVRE_DE_CAISSE!$O$4:$O$4701,LIVRE_DE_CAISSE!$G$4:$G$4701,A13,LIVRE_DE_CAISSE!$M$4:$M$4701,"Engagée")) | F13: =IF(A13="","",SUMIFS(LIVRE_DE_CAISSE!$O$4:$O$4701,LIVRE_DE_CAISSE!$G$4:$G$4701,A13,LIVRE_DE_CAISSE!$M$4:$M$4701,"Payée")) | G13: =IF(A13="","",E13+F13) | H13: =IF(A13="","",D13-G13) | I13: =IF(OR(A13="",N(D13)=0),"",G13/D13) | K13: =PARAMETRES!H12 | L13: =SUMIFS(LIVRE_DE_CAISSE!$N$4:$N$4701,LIVRE_DE_CAISSE!$E$4:$E$4701,K13) | M13: =SUMIFS(LIVRE_DE_CAISSE!$O$4:$O$4701,LIVRE_DE_CAISSE!$E$4:$E$4701,K13,LIVRE_DE_CAISSE!$M$4:$M$4701,"Payée") | N13: =SUMIFS(LIVRE_DE_CAISSE!$O$4:$O$4701,LIVRE_DE_CAISSE!$E$4:$E$4701,K13,LIVRE_DE_CAISSE!$M$4:$M$4701,"Engagée")
A14: =IF(BUDGET!A13="","",BUDGET!A13) | B14: =IF(A14="","",BUDGET!B13) | C14: =IF(A14="","",BUDGET!C13) | D14: =IF(A14="","",N(BUDGET!D13)) | E14: =IF(A14="","",SUMIFS(LIVRE_DE_CAISSE!$O$4:$O$4701,LIVRE_DE_CAISSE!$G$4:$G$4701,A14,LIVRE_DE_CAISSE!$M$4:$M$4701,"Engagée")) | F14: =IF(A14="","",SUMIFS(LIVRE_DE_CAISSE!$O$4:$O$4701,LIVRE_DE_CAISSE!$G$4:$G$4701,A14,LIVRE_DE_CAISSE!$M$4:$M$4701,"Payée")) | G14: =IF(A14="","",E14+F14) | H14: =IF(A14="","",D14-G14) | I14: =IF(OR(A14="",N(D14)=0),"",G14/D14) | K14: =PARAMETRES!H13 | L14: =SUMIFS(LIVRE_DE_CAISSE!$N$4:$N$4701,LIVRE_DE_CAISSE!$E$4:$E$4701,K14) | M14: =SUMIFS(LIVRE_DE_CAISSE!$O$4:$O$4701,LIVRE_DE_CAISSE!$E$4:$E$4701,K14,LIVRE_DE_CAISSE!$M$4:$M$4701,"Payée") | N14: =SUMIFS(LIVRE_DE_CAISSE!$O$4:$O$4701,LIVRE_DE_CAISSE!$E$4:$E$4701,K14,LIVRE_DE_CAISSE!$M$4:$M$4701,"Engagée")
K15: =PARAMETRES!H14 | L15: =SUMIFS(LIVRE_DE_CAISSE!$N$4:$N$4701,LIVRE_DE_CAISSE!$E$4:$E$4701,K15) | M15: =SUMIFS(LIVRE_DE_CAISSE!$O$4:$O$4701,LIVRE_DE_CAISSE!$E$4:$E$4701,K15,LIVRE_DE_CAISSE!$M$4:$M$4701,"Payée") | N15: =SUMIFS(LIVRE_DE_CAISSE!$O$4:$O$4701,LIVRE_DE_CAISSE!$E$4:$E$4701,K15,LIVRE_DE_CAISSE!$M$4:$M$4701,"Engagée")
K16: =PARAMETRES!H15 | L16: =SUMIFS(LIVRE_DE_CAISSE!$N$4:$N$4701,LIVRE_DE_CAISSE!$E$4:$E$4701,K16) | M16: =SUMIFS(LIVRE_DE_CAISSE!$O$4:$O$4701,LIVRE_DE_CAISSE!$E$4:$E$4701,K16,LIVRE_DE_CAISSE!$M$4:$M$4701,"Payée") | N16: =SUMIFS(LIVRE_DE_CAISSE!$O$4:$O$4701,LIVRE_DE_CAISSE!$E$4:$E$4701,K16,LIVRE_DE_CAISSE!$M$4:$M$4701,"Engagée")
K18: Solde de caisse | L18: =P_SOLDE_INITIAL+L4-M4

Sheet PARAMETRES
A1: PARAMÈTRES DU FICHIER DE SERVICE
A2: Cellules jaunes : modifiables. Les valeurs grisées sont renseignées par Administration et Finance ou par les macros.
B3: Libellé | C3: Valeur | E3: Modes de paiement | F3: Statuts | G3: Type d'opération | H3: Mois | I3: Catégories de dépenses
B4: Institution | C4: Inspection Générale des Finances (IGE) | E4: Espèces | F4: Payée | G4: Sortie | H4: Janvier | I4: Fournitures et petits matériels
B5: Code service | C5: 9990 TEST | E5: Chèque | F5: Engagée | G5: Entrée | H5: Février | I5: Carburant et lubrifiants
B6: Libellé du service | C6: 9990 TEST | E6: Virement | H6: Mars | I6: Entretien et réparation
B7: Exercice | C7: 2026 | E7: Mobile money | H7: Avril | I7: Communication et internet
B8: Devise | C8: CDF | H8: Mai | I8: Transport et déplacements
B9: Solde initial de caisse (report) | C9: 1000000 | H9: Juin | I9: Consommables Informatiques
B10: Dossier de transmission | C10: \\SERVEUR-IGE\IGE_FF\TRANSMISSIONS\ | H10: Juillet | I10: Produits Chimiques et Organiques
B11: Préfixe des fichiers de transmission | C11: TRANS_ | H11: Août | I11: Divers
B12: Dernier N° d'écriture attribué | C12: 0 | H12: Septembre
B13: Date de la dernière transmission | H13: Octobre
B14: Version du logiciel | C14: 1.0 | H14: Novembre
H15: Décembre

Sheet UTILISATEURS
A1: COMPTES AUTORISÉS POUR CE SERVICE
A2: Table remplie par Administration et Finance (macro GÉNÉRER LES FICHIERS SERVICES). Aucun mot de passe en clair : seule l'empreinte est conservée.
A3: Identifiant | B3: Empreinte du mot de passe | C3: Service attribué | D3: Profil | E3: Actif | F3: Changer MDP au prochain accès | G3: Dernière connexion
A4: agent8000 | C4: 8000 IG | D4: AGENT | E4: OUI | F4: OUI
A5: resp8000 | C5: 8000 IG | D5: RESPONSABLE | E5: OUI | F5: OUI

Sheet NOTICE
A1: NOTICE
A3: PROFILS
A4: AGENT : saisir des écritures, consulter le livre de caisse, le budget et le suivi budgétaire de son service, transmettre au centre.
A5: RESPONSABLE : droits de l'agent + modification du BUDGET, du solde initial et des catégories (feuille PARAMETRES).
A7: CIRCUIT D'UNE ÉCRITURE
A8: 1. FORMULAIRE_SAISIE → ENREGISTRER : contrôles (date dans l'exercice, rubrique existante, montant > 0, pièce si sortie, alertes solde et disponible).
A9: 2. L'écriture reçoit un identifiant unique ID_ECRITURE (ex. 8000IG-2026-000015) et l'état NON TRANSMISE dans le LIVRE_DE_CAISSE.
A10: 3. TRANSMETTRE AU CENTRE : crée TRANS_<service>_<date>.xlsx dans le dossier de transmission avec les seules écritures NON TRANSMISE ou A RETRANSMETTRE.
A11: 4. Les lignes envoyées passent à l'état TRANSMISE et reçoivent l'ID_TRANSMISSION.
A12: 5. Le paiement d'un engagement déjà transmis remet la ligne à l'état A RETRANSMETTRE : le centre mettra à jour la ligne existante (pas de doublon).
A14: RÈGLES
A15: - Le livre de caisse est protégé : aucune modification manuelle. Une erreur se corrige par une écriture inverse (contrepassation) avec une observation.
... A26: 7. Fermez le fichier ou cliquez sur SE DÉCONNECTER en fin de travail.
